[
  {
    "date":"2026-07-02",
    "tournament":"FIFA World Cup",
    "home_team":"Spain",
    "away_team":"Austria",
    "group":null,
    "tournament_stage":"round_of_32",
    "is_group_stage":false,
    "is_knockout_stage":true,
    "is_extra_time_possible":true,
    "is_penalty_possible":true,
    "model_home_expected_goals":2.3913333781,
    "model_away_expected_goals":0.7344994367,
    "context_home_expected_goals":2.3913333781,
    "context_away_expected_goals":0.7344994367,
    "context_home_attack_multiplier":1.0,
    "context_home_defense_multiplier":1.0,
    "context_away_attack_multiplier":1.0,
    "context_away_defense_multiplier":1.0,
    "context_draw_probability_multiplier":1.0,
    "context_applied":false,
    "context_confidence":null,
    "context_notes":null,
    "strategy_home_expected_goals":2.6782933835,
    "strategy_away_expected_goals":0.8226393691,
    "market_adjusted_home_expected_goals":2.6782933835,
    "market_adjusted_away_expected_goals":0.8226393691,
    "home_expected_goals":2.6782933835,
    "away_expected_goals":0.8226393691,
    "goal_inflation":1.4,
    "dynamic_goal_inflation":1.12,
    "stage_adjusted_goal_inflation":1.12,
    "dynamic_goal_inflation_reason":"knockout: clear favorite, late opening risk",
    "inflation_warning_flag":false,
    "inflation_warning_reason":null,
    "max_total_candidate_goals":4,
    "draw_probability_multiplier":1.0,
    "is_last_group_match":false,
    "home_needs_win":false,
    "away_needs_win":false,
    "home_draw_is_enough":false,
    "away_draw_is_enough":false,
    "competitive_context_applied":true,
    "home_already_qualified":false,
    "away_already_qualified":false,
    "home_eliminated":false,
    "away_eliminated":false,
    "home_goal_difference_pressure":false,
    "away_goal_difference_pressure":false,
    "match_pressure_score":1.0,
    "group_scenario_volatility":0.0,
    "home_must_advance":true,
    "away_must_advance":true,
    "knockout_match_importance":1.0,
    "extra_time_risk":0.1464693654,
    "penalty_risk":0.0659112144,
    "knockout_draw_boost":1.0,
    "favorite_caution_factor":0.98,
    "underdog_low_block_factor":1.03,
    "late_game_opening_factor":1.08,
    "home_win_probability":0.7616060516,
    "draw_probability":0.1464693654,
    "away_win_probability":0.091924583,
    "predicted_90min_scoreline":"3-1",
    "predicted_advancing_team":"Spain",
    "advancement_probability_home":0.8665354183,
    "advancement_probability_away":0.1334645817,
    "extra_time_probability":0.1464693654,
    "penalty_shootout_probability":0.0659112144,
    "market_home_win_probability":null,
    "market_draw_probability":null,
    "market_away_win_probability":null,
    "market_90min_home_probability":null,
    "market_90min_draw_probability":null,
    "market_90min_away_probability":null,
    "market_advance_home_probability":null,
    "market_advance_away_probability":null,
    "market_over_2_5_probability":null,
    "market_under_2_5_probability":null,
    "market_btts_yes_probability":null,
    "market_btts_no_probability":null,
    "market_btts_probability":null,
    "home_market_edge":null,
    "draw_market_edge":null,
    "away_market_edge":null,
    "market_disagreement_score":null,
    "market_warning_flag":false,
    "market_warning_reason":null,
    "risk_profile":"aggressive",
    "conservative_scoreline":"2-0",
    "conservative_expected_points":4.6809553215,
    "balanced_scoreline":"2-0",
    "balanced_expected_points":4.6809553215,
    "aggressive_scoreline":"3-1",
    "aggressive_expected_points":4.6223193082,
    "desperation_scoreline":"3-2",
    "desperation_expected_points":4.5150614259,
    "aggressive_total_goal_cap":4,
    "desperation_total_goal_cap":5,
    "risk_adjusted_candidate_scorelines":"2-0,2-1,3-1,1-0,3-0",
    "recommended_scoreline_by_risk":"3-1",
    "estimated_pick_popularity":0.5418441461,
    "differential_multiplier":1.3894324758,
    "upside_multiplier":1.32,
    "strategic_pick_value":8.4775687394,
    "expected_points_drop_vs_balanced":0.0125265057,
    "strategic_override_allowed":true,
    "strategic_override_reason":"expected-points drop within calibrated risk limit",
    "confidence_level":"high",
    "error_risk":"low",
    "main_reasons":"knockout: clear favorite, late opening risk",
    "alert_flags":"knockout_stage",
    "recommended_pick_type":"aggressive",
    "recommended_pick_explanation":"round_of_32: knockout: clear favorite, late opening risk; risk=aggressive; 90min 1X2 76.2%\/14.6%\/9.2%.",
    "safer_alternative_scoreline":"2-0",
    "safer_alternative_reason":"Higher-probability or lower-variance profile",
    "aggressive_alternative_scoreline":"3-1",
    "aggressive_alternative_reason":"Higher-upside profile within stage-adjusted goal cap",
    "model_warning_summary":null,
    "recommended_home_score":3,
    "recommended_away_score":1,
    "recommended_scoreline":"3-1",
    "recommended_expected_points":4.6223193082,
    "draw_alternative_home_score":1,
    "draw_alternative_away_score":1,
    "draw_alternative_scoreline":"1-1",
    "draw_alternative_expected_points":1.1500761083,
    "draw_alternative_is_competitive":false,
    "home_elo":2154.8066637076,
    "away_elo":1876.8174721124,
    "elo_diff":277.9891915952,
    "same_day_scoreline_count":1,
    "scoreline_diversity_penalty":0.0,
    "diversified_recommended_scoreline":"3-1"
  },
  {
    "date":"2026-07-02",
    "tournament":"FIFA World Cup",
    "home_team":"Portugal",
    "away_team":"Croatia",
    "group":null,
    "tournament_stage":"round_of_32",
    "is_group_stage":false,
    "is_knockout_stage":true,
    "is_extra_time_possible":true,
    "is_penalty_possible":true,
    "model_home_expected_goals":1.8849458556,
    "model_away_expected_goals":0.9508564683,
    "context_home_expected_goals":1.8849458556,
    "context_away_expected_goals":0.9508564683,
    "context_home_attack_multiplier":1.0,
    "context_home_defense_multiplier":1.0,
    "context_away_attack_multiplier":1.0,
    "context_away_defense_multiplier":1.0,
    "context_draw_probability_multiplier":1.0,
    "context_applied":false,
    "context_confidence":null,
    "context_notes":null,
    "strategy_home_expected_goals":2.1111393582,
    "strategy_away_expected_goals":1.0649592445,
    "market_adjusted_home_expected_goals":2.1111393582,
    "market_adjusted_away_expected_goals":1.0649592445,
    "home_expected_goals":2.1111393582,
    "away_expected_goals":1.0649592445,
    "goal_inflation":1.4,
    "dynamic_goal_inflation":1.12,
    "stage_adjusted_goal_inflation":1.12,
    "dynamic_goal_inflation_reason":"knockout: moderate favorite, controlled tempo",
    "inflation_warning_flag":false,
    "inflation_warning_reason":null,
    "max_total_candidate_goals":4,
    "draw_probability_multiplier":1.04,
    "is_last_group_match":false,
    "home_needs_win":false,
    "away_needs_win":false,
    "home_draw_is_enough":false,
    "away_draw_is_enough":false,
    "competitive_context_applied":true,
    "home_already_qualified":false,
    "away_already_qualified":false,
    "home_eliminated":false,
    "away_eliminated":false,
    "home_goal_difference_pressure":false,
    "away_goal_difference_pressure":false,
    "match_pressure_score":1.0,
    "group_scenario_volatility":0.0,
    "home_must_advance":true,
    "away_must_advance":true,
    "knockout_match_importance":1.0,
    "extra_time_risk":0.2112958123,
    "penalty_risk":0.0950831155,
    "knockout_draw_boost":1.04,
    "favorite_caution_factor":0.96,
    "underdog_low_block_factor":1.06,
    "late_game_opening_factor":1.04,
    "home_win_probability":0.6062543193,
    "draw_probability":0.2112958123,
    "away_win_probability":0.1824498684,
    "predicted_90min_scoreline":"3-1",
    "predicted_advancing_team":"Portugal",
    "advancement_probability_home":0.7277891219,
    "advancement_probability_away":0.2722108781,
    "extra_time_probability":0.2112958123,
    "penalty_shootout_probability":0.0950831155,
    "market_home_win_probability":null,
    "market_draw_probability":null,
    "market_away_win_probability":null,
    "market_90min_home_probability":null,
    "market_90min_draw_probability":null,
    "market_90min_away_probability":null,
    "market_advance_home_probability":null,
    "market_advance_away_probability":null,
    "market_over_2_5_probability":null,
    "market_under_2_5_probability":null,
    "market_btts_yes_probability":null,
    "market_btts_no_probability":null,
    "market_btts_probability":null,
    "home_market_edge":null,
    "draw_market_edge":null,
    "away_market_edge":null,
    "market_disagreement_score":null,
    "market_warning_flag":false,
    "market_warning_reason":null,
    "risk_profile":"aggressive",
    "conservative_scoreline":"2-1",
    "conservative_expected_points":3.9240518595,
    "balanced_scoreline":"2-1",
    "balanced_expected_points":3.9240518595,
    "aggressive_scoreline":"3-1",
    "aggressive_expected_points":3.7260169396,
    "desperation_scoreline":"3-2",
    "desperation_expected_points":3.8003949026,
    "aggressive_total_goal_cap":4,
    "desperation_total_goal_cap":5,
    "risk_adjusted_candidate_scorelines":"2-1,1-0,2-0,3-1,3-0",
    "recommended_scoreline_by_risk":"3-1",
    "estimated_pick_popularity":0.484562329,
    "differential_multiplier":1.4381220204,
    "upside_multiplier":1.32,
    "strategic_pick_value":7.073176452,
    "expected_points_drop_vs_balanced":0.0504669477,
    "strategic_override_allowed":true,
    "strategic_override_reason":"expected-points drop within calibrated risk limit",
    "confidence_level":"medium",
    "error_risk":"low",
    "main_reasons":"knockout: moderate favorite, controlled tempo",
    "alert_flags":"knockout_stage",
    "recommended_pick_type":"aggressive",
    "recommended_pick_explanation":"round_of_32: knockout: moderate favorite, controlled tempo; risk=aggressive; 90min 1X2 60.6%\/21.1%\/18.2%.",
    "safer_alternative_scoreline":"2-1",
    "safer_alternative_reason":"Higher-probability or lower-variance profile",
    "aggressive_alternative_scoreline":"3-1",
    "aggressive_alternative_reason":"Higher-upside profile within stage-adjusted goal cap",
    "model_warning_summary":null,
    "recommended_home_score":3,
    "recommended_away_score":1,
    "recommended_scoreline":"3-1",
    "recommended_expected_points":3.7260169396,
    "draw_alternative_home_score":1,
    "draw_alternative_away_score":1,
    "draw_alternative_scoreline":"1-1",
    "draw_alternative_expected_points":1.6574615088,
    "draw_alternative_is_competitive":false,
    "home_elo":2034.6460990464,
    "away_elo":1943.73110701,
    "elo_diff":90.9149920364,
    "same_day_scoreline_count":2,
    "scoreline_diversity_penalty":0.0,
    "diversified_recommended_scoreline":"3-1"
  },
  {
    "date":"2026-07-02",
    "tournament":"FIFA World Cup",
    "home_team":"Switzerland",
    "away_team":"Algeria",
    "group":null,
    "tournament_stage":"round_of_32",
    "is_group_stage":false,
    "is_knockout_stage":true,
    "is_extra_time_possible":true,
    "is_penalty_possible":true,
    "model_home_expected_goals":1.5845588905,
    "model_away_expected_goals":1.1152665662,
    "context_home_expected_goals":1.5845588905,
    "context_away_expected_goals":1.1152665662,
    "context_home_attack_multiplier":1.0,
    "context_home_defense_multiplier":1.0,
    "context_away_attack_multiplier":1.0,
    "context_away_defense_multiplier":1.0,
    "context_draw_probability_multiplier":1.0,
    "context_applied":false,
    "context_confidence":null,
    "context_notes":null,
    "strategy_home_expected_goals":1.7113236018,
    "strategy_away_expected_goals":1.2044878915,
    "market_adjusted_home_expected_goals":1.7113236018,
    "market_adjusted_away_expected_goals":1.2044878915,
    "home_expected_goals":1.7113236018,
    "away_expected_goals":1.2044878915,
    "goal_inflation":1.4,
    "dynamic_goal_inflation":1.08,
    "stage_adjusted_goal_inflation":1.08,
    "dynamic_goal_inflation_reason":"knockout: balanced tie, draw boosted, goals dampened",
    "inflation_warning_flag":false,
    "inflation_warning_reason":null,
    "max_total_candidate_goals":4,
    "draw_probability_multiplier":1.12,
    "is_last_group_match":false,
    "home_needs_win":false,
    "away_needs_win":false,
    "home_draw_is_enough":false,
    "away_draw_is_enough":false,
    "competitive_context_applied":true,
    "home_already_qualified":false,
    "away_already_qualified":false,
    "home_eliminated":false,
    "away_eliminated":false,
    "home_goal_difference_pressure":false,
    "away_goal_difference_pressure":false,
    "match_pressure_score":1.0,
    "group_scenario_volatility":0.0,
    "home_must_advance":true,
    "away_must_advance":true,
    "knockout_match_importance":1.0,
    "extra_time_risk":0.2600846089,
    "penalty_risk":0.117038074,
    "knockout_draw_boost":1.12,
    "favorite_caution_factor":0.92,
    "underdog_low_block_factor":1.1,
    "late_game_opening_factor":1.02,
    "home_win_probability":0.4780033875,
    "draw_probability":0.2600846089,
    "away_win_probability":0.2619120037,
    "predicted_90min_scoreline":"1-1",
    "predicted_advancing_team":"Switzerland",
    "advancement_probability_home":0.6214144346,
    "advancement_probability_away":0.3785855654,
    "extra_time_probability":0.2600846089,
    "penalty_shootout_probability":0.117038074,
    "market_home_win_probability":null,
    "market_draw_probability":null,
    "market_away_win_probability":null,
    "market_90min_home_probability":null,
    "market_90min_draw_probability":null,
    "market_90min_away_probability":null,
    "market_advance_home_probability":null,
    "market_advance_away_probability":null,
    "market_over_2_5_probability":null,
    "market_under_2_5_probability":null,
    "market_btts_yes_probability":null,
    "market_btts_no_probability":null,
    "market_btts_probability":null,
    "home_market_edge":null,
    "draw_market_edge":null,
    "away_market_edge":null,
    "market_disagreement_score":null,
    "market_warning_flag":false,
    "market_warning_reason":null,
    "risk_profile":"aggressive",
    "conservative_scoreline":"2-1",
    "conservative_expected_points":3.2404696558,
    "balanced_scoreline":"2-1",
    "balanced_expected_points":3.2404696558,
    "aggressive_scoreline":"3-1",
    "aggressive_expected_points":2.9344283046,
    "desperation_scoreline":"3-1",
    "desperation_expected_points":2.9344283046,
    "aggressive_total_goal_cap":4,
    "desperation_total_goal_cap":4,
    "risk_adjusted_candidate_scorelines":"2-1,1-0,2-0,3-1",
    "recommended_scoreline_by_risk":"3-1",
    "estimated_pick_popularity":0.3455883474,
    "differential_multiplier":1.5562499047,
    "upside_multiplier":1.32,
    "strategic_pick_value":5.4252440781,
    "expected_points_drop_vs_balanced":0.0944435171,
    "strategic_override_allowed":true,
    "strategic_override_reason":"expected-points drop within calibrated risk limit",
    "confidence_level":"low",
    "error_risk":"medium",
    "main_reasons":"knockout: balanced tie, draw boosted, goals dampened",
    "alert_flags":"knockout_stage,daily_scoreline_diversity_penalty",
    "recommended_pick_type":"aggressive",
    "recommended_pick_explanation":"round_of_32: knockout: balanced tie, draw boosted, goals dampened; risk=aggressive; 90min 1X2 47.8%\/26.0%\/26.2%. Diversity layer moved the pick to a lower-duplication alternative.",
    "safer_alternative_scoreline":"2-1",
    "safer_alternative_reason":"Higher-probability or lower-variance profile",
    "aggressive_alternative_scoreline":"3-1",
    "aggressive_alternative_reason":"Higher-upside profile within stage-adjusted goal cap",
    "model_warning_summary":"Same scoreline repeated 3+ times on date",
    "recommended_home_score":1,
    "recommended_away_score":1,
    "recommended_scoreline":"1-1",
    "recommended_expected_points":2.0477836615,
    "draw_alternative_home_score":1,
    "draw_alternative_away_score":1,
    "draw_alternative_scoreline":"1-1",
    "draw_alternative_expected_points":2.0477836615,
    "draw_alternative_is_competitive":false,
    "home_elo":1936.9715609824,
    "away_elo":1875.0710617646,
    "elo_diff":61.9004992179,
    "same_day_scoreline_count":3,
    "scoreline_diversity_penalty":0.1,
    "diversified_recommended_scoreline":"1-1"
  },
  {
    "date":"2026-07-03",
    "tournament":"FIFA World Cup",
    "home_team":"Australia",
    "away_team":"Egypt",
    "group":null,
    "tournament_stage":"round_of_32",
    "is_group_stage":false,
    "is_knockout_stage":true,
    "is_extra_time_possible":true,
    "is_penalty_possible":true,
    "model_home_expected_goals":1.4680901904,
    "model_away_expected_goals":0.9335081783,
    "context_home_expected_goals":1.4680901904,
    "context_away_expected_goals":0.9335081783,
    "context_home_attack_multiplier":1.0,
    "context_home_defense_multiplier":1.0,
    "context_away_attack_multiplier":1.0,
    "context_away_defense_multiplier":1.0,
    "context_draw_probability_multiplier":1.0,
    "context_applied":false,
    "context_confidence":null,
    "context_notes":null,
    "strategy_home_expected_goals":1.6442610133,
    "strategy_away_expected_goals":1.0455291597,
    "market_adjusted_home_expected_goals":1.6442610133,
    "market_adjusted_away_expected_goals":1.0455291597,
    "home_expected_goals":1.6442610133,
    "away_expected_goals":1.0455291597,
    "goal_inflation":1.4,
    "dynamic_goal_inflation":1.12,
    "stage_adjusted_goal_inflation":1.12,
    "dynamic_goal_inflation_reason":"knockout: moderate favorite, controlled tempo",
    "inflation_warning_flag":false,
    "inflation_warning_reason":null,
    "max_total_candidate_goals":4,
    "draw_probability_multiplier":1.04,
    "is_last_group_match":false,
    "home_needs_win":false,
    "away_needs_win":false,
    "home_draw_is_enough":false,
    "away_draw_is_enough":false,
    "competitive_context_applied":true,
    "home_already_qualified":false,
    "away_already_qualified":false,
    "home_eliminated":false,
    "away_eliminated":false,
    "home_goal_difference_pressure":false,
    "away_goal_difference_pressure":false,
    "match_pressure_score":1.0,
    "group_scenario_volatility":0.0,
    "home_must_advance":true,
    "away_must_advance":true,
    "knockout_match_importance":1.0,
    "extra_time_risk":0.2532194095,
    "penalty_risk":0.1139487343,
    "knockout_draw_boost":1.04,
    "favorite_caution_factor":0.96,
    "underdog_low_block_factor":1.06,
    "late_game_opening_factor":1.04,
    "home_win_probability":0.507726091,
    "draw_probability":0.2532194095,
    "away_win_probability":0.2390544995,
    "predicted_90min_scoreline":"2-1",
    "predicted_advancing_team":"Australia",
    "advancement_probability_home":0.6524614575,
    "advancement_probability_away":0.3475385425,
    "extra_time_probability":0.2532194095,
    "penalty_shootout_probability":0.1139487343,
    "market_home_win_probability":null,
    "market_draw_probability":null,
    "market_away_win_probability":null,
    "market_90min_home_probability":null,
    "market_90min_draw_probability":null,
    "market_90min_away_probability":null,
    "market_advance_home_probability":null,
    "market_advance_away_probability":null,
    "market_over_2_5_probability":null,
    "market_under_2_5_probability":null,
    "market_btts_yes_probability":null,
    "market_btts_no_probability":null,
    "market_btts_probability":null,
    "home_market_edge":null,
    "draw_market_edge":null,
    "away_market_edge":null,
    "market_disagreement_score":null,
    "market_warning_flag":false,
    "market_warning_reason":null,
    "risk_profile":"aggressive",
    "conservative_scoreline":"1-0",
    "conservative_expected_points":3.4724553789,
    "balanced_scoreline":"1-0",
    "balanced_expected_points":3.4724553789,
    "aggressive_scoreline":"2-1",
    "aggressive_expected_points":3.4413525456,
    "desperation_scoreline":"3-1",
    "desperation_expected_points":3.1103511037,
    "aggressive_total_goal_cap":4,
    "desperation_total_goal_cap":4,
    "risk_adjusted_candidate_scorelines":"1-0,2-1,2-0",
    "recommended_scoreline_by_risk":"2-1",
    "estimated_pick_popularity":0.6195589838,
    "differential_multiplier":1.3233748638,
    "upside_multiplier":1.22,
    "strategic_pick_value":5.5561233366,
    "expected_points_drop_vs_balanced":0.0089570145,
    "strategic_override_allowed":true,
    "strategic_override_reason":"expected-points drop within calibrated risk limit",
    "confidence_level":"low",
    "error_risk":"medium",
    "main_reasons":"knockout: moderate favorite, controlled tempo",
    "alert_flags":"knockout_stage",
    "recommended_pick_type":"aggressive",
    "recommended_pick_explanation":"round_of_32: knockout: moderate favorite, controlled tempo; risk=aggressive; 90min 1X2 50.8%\/25.3%\/23.9%.",
    "safer_alternative_scoreline":"1-0",
    "safer_alternative_reason":"Higher-probability or lower-variance profile",
    "aggressive_alternative_scoreline":"2-1",
    "aggressive_alternative_reason":"Higher-upside profile within stage-adjusted goal cap",
    "model_warning_summary":null,
    "recommended_home_score":2,
    "recommended_away_score":1,
    "recommended_scoreline":"2-1",
    "recommended_expected_points":3.4413525456,
    "draw_alternative_home_score":1,
    "draw_alternative_away_score":1,
    "draw_alternative_scoreline":"1-1",
    "draw_alternative_expected_points":2.0009458696,
    "draw_alternative_is_competitive":false,
    "home_elo":1889.8727518205,
    "away_elo":1803.3815750074,
    "elo_diff":86.4911768132,
    "same_day_scoreline_count":1,
    "scoreline_diversity_penalty":0.0,
    "diversified_recommended_scoreline":"2-1"
  },
  {
    "date":"2026-07-03",
    "tournament":"FIFA World Cup",
    "home_team":"Argentina",
    "away_team":"Cape Verde",
    "group":null,
    "tournament_stage":"round_of_32",
    "is_group_stage":false,
    "is_knockout_stage":true,
    "is_extra_time_possible":true,
    "is_penalty_possible":true,
    "model_home_expected_goals":2.9856151959,
    "model_away_expected_goals":0.4961855858,
    "context_home_expected_goals":2.9856151959,
    "context_away_expected_goals":0.4961855858,
    "context_home_attack_multiplier":1.0,
    "context_home_defense_multiplier":1.0,
    "context_away_attack_multiplier":1.0,
    "context_away_defense_multiplier":1.0,
    "context_draw_probability_multiplier":1.0,
    "context_applied":false,
    "context_confidence":null,
    "context_notes":null,
    "strategy_home_expected_goals":3.5230259311,
    "strategy_away_expected_goals":0.5854989912,
    "market_adjusted_home_expected_goals":3.5230259311,
    "market_adjusted_away_expected_goals":0.5854989912,
    "home_expected_goals":3.5230259311,
    "away_expected_goals":0.5854989912,
    "goal_inflation":1.4,
    "dynamic_goal_inflation":1.18,
    "stage_adjusted_goal_inflation":1.18,
    "dynamic_goal_inflation_reason":"knockout: strong favorite, late opening risk",
    "inflation_warning_flag":false,
    "inflation_warning_reason":null,
    "max_total_candidate_goals":4,
    "draw_probability_multiplier":1.0,
    "is_last_group_match":false,
    "home_needs_win":false,
    "away_needs_win":false,
    "home_draw_is_enough":false,
    "away_draw_is_enough":false,
    "competitive_context_applied":true,
    "home_already_qualified":false,
    "away_already_qualified":false,
    "home_eliminated":false,
    "away_eliminated":false,
    "home_goal_difference_pressure":false,
    "away_goal_difference_pressure":false,
    "match_pressure_score":1.0,
    "group_scenario_volatility":0.0,
    "home_must_advance":true,
    "away_must_advance":true,
    "knockout_match_importance":1.0,
    "extra_time_risk":0.0775770973,
    "penalty_risk":0.0349096938,
    "knockout_draw_boost":1.0,
    "favorite_caution_factor":0.98,
    "underdog_low_block_factor":1.03,
    "late_game_opening_factor":1.1,
    "home_win_probability":0.8903042175,
    "draw_probability":0.0775770973,
    "away_win_probability":0.0321186852,
    "predicted_90min_scoreline":"4-0",
    "predicted_advancing_team":"Argentina",
    "advancement_probability_home":0.9561055185,
    "advancement_probability_away":0.0438944815,
    "extra_time_probability":0.0775770973,
    "penalty_shootout_probability":0.0349096938,
    "market_home_win_probability":null,
    "market_draw_probability":null,
    "market_away_win_probability":null,
    "market_90min_home_probability":null,
    "market_90min_draw_probability":null,
    "market_90min_away_probability":null,
    "market_advance_home_probability":null,
    "market_advance_away_probability":null,
    "market_over_2_5_probability":null,
    "market_under_2_5_probability":null,
    "market_btts_yes_probability":null,
    "market_btts_no_probability":null,
    "market_btts_probability":null,
    "home_market_edge":null,
    "draw_market_edge":null,
    "away_market_edge":null,
    "market_disagreement_score":null,
    "market_warning_flag":false,
    "market_warning_reason":null,
    "risk_profile":"aggressive",
    "conservative_scoreline":"3-0",
    "conservative_expected_points":5.3375813164,
    "balanced_scoreline":"3-0",
    "balanced_expected_points":5.3375813164,
    "aggressive_scoreline":"4-0",
    "aggressive_expected_points":5.180782999,
    "desperation_scoreline":"4-1",
    "desperation_expected_points":5.2132435646,
    "aggressive_total_goal_cap":4,
    "desperation_total_goal_cap":5,
    "risk_adjusted_candidate_scorelines":"3-0,2-0,3-1,4-0,2-1",
    "recommended_scoreline_by_risk":"4-0",
    "estimated_pick_popularity":0.6349953904,
    "differential_multiplier":1.3102539181,
    "upside_multiplier":1.4,
    "strategic_pick_value":9.5033977128,
    "expected_points_drop_vs_balanced":0.0293762864,
    "strategic_override_allowed":true,
    "strategic_override_reason":"expected-points drop within calibrated risk limit",
    "confidence_level":"high",
    "error_risk":"low",
    "main_reasons":"knockout: strong favorite, late opening risk",
    "alert_flags":"knockout_stage",
    "recommended_pick_type":"aggressive",
    "recommended_pick_explanation":"round_of_32: knockout: strong favorite, late opening risk; risk=aggressive; 90min 1X2 89.0%\/7.8%\/3.2%.",
    "safer_alternative_scoreline":"3-0",
    "safer_alternative_reason":"Higher-probability or lower-variance profile",
    "aggressive_alternative_scoreline":"4-0",
    "aggressive_alternative_reason":"Higher-upside profile within stage-adjusted goal cap",
    "model_warning_summary":null,
    "recommended_home_score":4,
    "recommended_away_score":0,
    "recommended_scoreline":"4-0",
    "recommended_expected_points":5.180782999,
    "draw_alternative_home_score":1,
    "draw_alternative_away_score":1,
    "draw_alternative_scoreline":"1-1",
    "draw_alternative_expected_points":0.610790199,
    "draw_alternative_is_competitive":false,
    "home_elo":2167.9876663031,
    "away_elo":1651.809664877,
    "elo_diff":516.1780014262,
    "same_day_scoreline_count":1,
    "scoreline_diversity_penalty":0.0,
    "diversified_recommended_scoreline":"4-0"
  },
  {
    "date":"2026-07-03",
    "tournament":"FIFA World Cup",
    "home_team":"Colombia",
    "away_team":"Ghana",
    "group":null,
    "tournament_stage":"round_of_32",
    "is_group_stage":false,
    "is_knockout_stage":true,
    "is_extra_time_possible":true,
    "is_penalty_possible":true,
    "model_home_expected_goals":2.4352442214,
    "model_away_expected_goals":0.5504182193,
    "context_home_expected_goals":2.4352442214,
    "context_away_expected_goals":0.5504182193,
    "context_home_attack_multiplier":1.0,
    "context_home_defense_multiplier":1.0,
    "context_away_attack_multiplier":1.0,
    "context_away_defense_multiplier":1.0,
    "context_draw_probability_multiplier":1.0,
    "context_applied":false,
    "context_confidence":null,
    "context_notes":null,
    "strategy_home_expected_goals":2.8735881812,
    "strategy_away_expected_goals":0.6494934988,
    "market_adjusted_home_expected_goals":2.8735881812,
    "market_adjusted_away_expected_goals":0.6494934988,
    "home_expected_goals":2.8735881812,
    "away_expected_goals":0.6494934988,
    "goal_inflation":1.4,
    "dynamic_goal_inflation":1.18,
    "stage_adjusted_goal_inflation":1.18,
    "dynamic_goal_inflation_reason":"knockout: strong favorite, late opening risk",
    "inflation_warning_flag":false,
    "inflation_warning_reason":null,
    "max_total_candidate_goals":4,
    "draw_probability_multiplier":1.0,
    "is_last_group_match":false,
    "home_needs_win":false,
    "away_needs_win":false,
    "home_draw_is_enough":false,
    "away_draw_is_enough":false,
    "competitive_context_applied":true,
    "home_already_qualified":false,
    "away_already_qualified":false,
    "home_eliminated":false,
    "away_eliminated":false,
    "home_goal_difference_pressure":false,
    "away_goal_difference_pressure":false,
    "match_pressure_score":1.0,
    "group_scenario_volatility":0.0,
    "home_must_advance":true,
    "away_must_advance":true,
    "knockout_match_importance":1.0,
    "extra_time_risk":0.1195713162,
    "penalty_risk":0.0538070923,
    "knockout_draw_boost":1.0,
    "favorite_caution_factor":0.98,
    "underdog_low_block_factor":1.03,
    "late_game_opening_factor":1.1,
    "home_win_probability":0.8216658664,
    "draw_probability":0.1195713162,
    "away_win_probability":0.0587628174,
    "predicted_90min_scoreline":"3-1",
    "predicted_advancing_team":"Colombia",
    "advancement_probability_home":0.9153733731,
    "advancement_probability_away":0.0846266269,
    "extra_time_probability":0.1195713162,
    "penalty_shootout_probability":0.0538070923,
    "market_home_win_probability":null,
    "market_draw_probability":null,
    "market_away_win_probability":null,
    "market_90min_home_probability":null,
    "market_90min_draw_probability":null,
    "market_90min_away_probability":null,
    "market_advance_home_probability":null,
    "market_advance_away_probability":null,
    "market_over_2_5_probability":null,
    "market_under_2_5_probability":null,
    "market_btts_yes_probability":null,
    "market_btts_no_probability":null,
    "market_btts_probability":null,
    "home_market_edge":null,
    "draw_market_edge":null,
    "away_market_edge":null,
    "market_disagreement_score":null,
    "market_warning_flag":false,
    "market_warning_reason":null,
    "risk_profile":"aggressive",
    "conservative_scoreline":"2-0",
    "conservative_expected_points":5.0304346478,
    "balanced_scoreline":"2-0",
    "balanced_expected_points":5.0304346478,
    "aggressive_scoreline":"3-1",
    "aggressive_expected_points":4.9357522828,
    "desperation_scoreline":"4-1",
    "desperation_expected_points":4.7829079949,
    "aggressive_total_goal_cap":4,
    "desperation_total_goal_cap":5,
    "risk_adjusted_candidate_scorelines":"2-0,3-1,3-0,1-0,2-1",
    "recommended_scoreline_by_risk":"3-1",
    "estimated_pick_popularity":0.5170532468,
    "differential_multiplier":1.4105047402,
    "upside_multiplier":1.32,
    "strategic_pick_value":9.1897106288,
    "expected_points_drop_vs_balanced":0.0188219054,
    "strategic_override_allowed":true,
    "strategic_override_reason":"expected-points drop within calibrated risk limit",
    "confidence_level":"high",
    "error_risk":"low",
    "main_reasons":"knockout: strong favorite, late opening risk",
    "alert_flags":"knockout_stage",
    "recommended_pick_type":"aggressive",
    "recommended_pick_explanation":"round_of_32: knockout: strong favorite, late opening risk; risk=aggressive; 90min 1X2 82.2%\/12.0%\/5.9%.",
    "safer_alternative_scoreline":"2-0",
    "safer_alternative_reason":"Higher-probability or lower-variance profile",
    "aggressive_alternative_scoreline":"3-1",
    "aggressive_alternative_reason":"Higher-upside profile within stage-adjusted goal cap",
    "model_warning_summary":null,
    "recommended_home_score":3,
    "recommended_away_score":1,
    "recommended_scoreline":"3-1",
    "recommended_expected_points":4.9357522828,
    "draw_alternative_home_score":1,
    "draw_alternative_away_score":1,
    "draw_alternative_scoreline":"1-1",
    "draw_alternative_expected_points":0.9439611253,
    "draw_alternative_is_competitive":false,
    "home_elo":2045.5510218409,
    "away_elo":1659.3509345955,
    "elo_diff":386.2000872454,
    "same_day_scoreline_count":1,
    "scoreline_diversity_penalty":0.0,
    "diversified_recommended_scoreline":"3-1"
  },
  {
    "date":"2026-07-04",
    "tournament":"FIFA World Cup",
    "home_team":"Canada",
    "away_team":"Morocco",
    "group":null,
    "tournament_stage":"round_of_16",
    "is_group_stage":false,
    "is_knockout_stage":true,
    "is_extra_time_possible":true,
    "is_penalty_possible":true,
    "model_home_expected_goals":1.0510946267,
    "model_away_expected_goals":1.4215236043,
    "context_home_expected_goals":1.0510946267,
    "context_away_expected_goals":1.4215236043,
    "context_home_attack_multiplier":1.0,
    "context_home_defense_multiplier":1.0,
    "context_away_attack_multiplier":1.0,
    "context_away_defense_multiplier":1.0,
    "context_draw_probability_multiplier":1.0,
    "context_applied":false,
    "context_confidence":null,
    "context_notes":null,
    "strategy_home_expected_goals":1.1772259819,
    "strategy_away_expected_goals":1.5921064369,
    "market_adjusted_home_expected_goals":1.1772259819,
    "market_adjusted_away_expected_goals":1.5921064369,
    "home_expected_goals":1.1772259819,
    "away_expected_goals":1.5921064369,
    "goal_inflation":1.4,
    "dynamic_goal_inflation":1.12,
    "stage_adjusted_goal_inflation":1.12,
    "dynamic_goal_inflation_reason":"knockout: moderate favorite, controlled tempo",
    "inflation_warning_flag":false,
    "inflation_warning_reason":null,
    "max_total_candidate_goals":4,
    "draw_probability_multiplier":1.04,
    "is_last_group_match":false,
    "home_needs_win":false,
    "away_needs_win":false,
    "home_draw_is_enough":false,
    "away_draw_is_enough":false,
    "competitive_context_applied":true,
    "home_already_qualified":false,
    "away_already_qualified":false,
    "home_eliminated":false,
    "away_eliminated":false,
    "home_goal_difference_pressure":false,
    "away_goal_difference_pressure":false,
    "match_pressure_score":1.0,
    "group_scenario_volatility":0.0,
    "home_must_advance":true,
    "away_must_advance":true,
    "knockout_match_importance":1.0,
    "extra_time_risk":0.2559896269,
    "penalty_risk":0.1151953321,
    "knockout_draw_boost":1.04,
    "favorite_caution_factor":0.96,
    "underdog_low_block_factor":1.06,
    "late_game_opening_factor":1.04,
    "home_win_probability":0.2794423248,
    "draw_probability":0.2559896269,
    "away_win_probability":0.4645680483,
    "predicted_90min_scoreline":"1-2",
    "predicted_advancing_team":"Morocco",
    "advancement_probability_home":0.3850104398,
    "advancement_probability_away":0.6149895602,
    "extra_time_probability":0.2559896269,
    "penalty_shootout_probability":0.1151953321,
    "market_home_win_probability":null,
    "market_draw_probability":null,
    "market_away_win_probability":null,
    "market_90min_home_probability":null,
    "market_90min_draw_probability":null,
    "market_90min_away_probability":null,
    "market_advance_home_probability":null,
    "market_advance_away_probability":null,
    "market_over_2_5_probability":null,
    "market_under_2_5_probability":null,
    "market_btts_yes_probability":null,
    "market_btts_no_probability":null,
    "market_btts_probability":null,
    "home_market_edge":null,
    "draw_market_edge":null,
    "away_market_edge":null,
    "market_disagreement_score":null,
    "market_warning_flag":false,
    "market_warning_reason":null,
    "risk_profile":"aggressive",
    "conservative_scoreline":"0-1",
    "conservative_expected_points":3.1980363372,
    "balanced_scoreline":"0-1",
    "balanced_expected_points":3.1980363372,
    "aggressive_scoreline":"1-2",
    "aggressive_expected_points":3.185589096,
    "desperation_scoreline":"1-3",
    "desperation_expected_points":2.8447136383,
    "aggressive_total_goal_cap":4,
    "desperation_total_goal_cap":4,
    "risk_adjusted_candidate_scorelines":"0-1,1-2,0-2",
    "recommended_scoreline_by_risk":"1-2",
    "estimated_pick_popularity":0.5805613274,
    "differential_multiplier":1.3565228718,
    "upside_multiplier":1.22,
    "strategic_pick_value":5.2720158518,
    "expected_points_drop_vs_balanced":0.0038921513,
    "strategic_override_allowed":true,
    "strategic_override_reason":"expected-points drop within calibrated risk limit",
    "confidence_level":"low",
    "error_risk":"medium",
    "main_reasons":"knockout: moderate favorite, controlled tempo",
    "alert_flags":"knockout_stage",
    "recommended_pick_type":"aggressive",
    "recommended_pick_explanation":"round_of_16: knockout: moderate favorite, controlled tempo; risk=aggressive; 90min 1X2 27.9%\/25.6%\/46.5%.",
    "safer_alternative_scoreline":"0-1",
    "safer_alternative_reason":"Higher-probability or lower-variance profile",
    "aggressive_alternative_scoreline":"1-2",
    "aggressive_alternative_reason":"Higher-upside profile within stage-adjusted goal cap",
    "model_warning_summary":null,
    "recommended_home_score":1,
    "recommended_away_score":2,
    "recommended_scoreline":"1-2",
    "recommended_expected_points":3.185589096,
    "draw_alternative_home_score":1,
    "draw_alternative_away_score":1,
    "draw_alternative_scoreline":"1-1",
    "draw_alternative_expected_points":2.0207617763,
    "draw_alternative_is_competitive":false,
    "home_elo":1873.389213064,
    "away_elo":1979.6147272518,
    "elo_diff":-106.2255141878,
    "same_day_scoreline_count":1,
    "scoreline_diversity_penalty":0.0,
    "diversified_recommended_scoreline":"1-2"
  },
  {
    "date":"2026-07-04",
    "tournament":"FIFA World Cup",
    "home_team":"Paraguay",
    "away_team":"France",
    "group":null,
    "tournament_stage":"round_of_16",
    "is_group_stage":false,
    "is_knockout_stage":true,
    "is_extra_time_possible":true,
    "is_penalty_possible":true,
    "model_home_expected_goals":0.8124242972,
    "model_away_expected_goals":2.0844466196,
    "context_home_expected_goals":0.8124242972,
    "context_away_expected_goals":2.0844466196,
    "context_home_attack_multiplier":1.0,
    "context_home_defense_multiplier":1.0,
    "context_away_attack_multiplier":1.0,
    "context_away_defense_multiplier":1.0,
    "context_draw_probability_multiplier":1.0,
    "context_applied":false,
    "context_confidence":null,
    "context_notes":null,
    "strategy_home_expected_goals":0.9099152128,
    "strategy_away_expected_goals":2.3345802139,
    "market_adjusted_home_expected_goals":0.9099152128,
    "market_adjusted_away_expected_goals":2.3345802139,
    "home_expected_goals":0.9099152128,
    "away_expected_goals":2.3345802139,
    "goal_inflation":1.4,
    "dynamic_goal_inflation":1.12,
    "stage_adjusted_goal_inflation":1.12,
    "dynamic_goal_inflation_reason":"knockout: clear favorite, late opening risk",
    "inflation_warning_flag":false,
    "inflation_warning_reason":null,
    "max_total_candidate_goals":4,
    "draw_probability_multiplier":1.0,
    "is_last_group_match":false,
    "home_needs_win":false,
    "away_needs_win":false,
    "home_draw_is_enough":false,
    "away_draw_is_enough":false,
    "competitive_context_applied":true,
    "home_already_qualified":false,
    "away_already_qualified":false,
    "home_eliminated":false,
    "away_eliminated":false,
    "home_goal_difference_pressure":false,
    "away_goal_difference_pressure":false,
    "match_pressure_score":1.0,
    "group_scenario_volatility":0.0,
    "home_must_advance":true,
    "away_must_advance":true,
    "knockout_match_importance":1.0,
    "extra_time_risk":0.1794976886,
    "penalty_risk":0.0807739599,
    "knockout_draw_boost":1.0,
    "favorite_caution_factor":0.98,
    "underdog_low_block_factor":1.03,
    "late_game_opening_factor":1.08,
    "home_win_probability":0.1316210399,
    "draw_probability":0.1794976886,
    "away_win_probability":0.6888812715,
    "predicted_90min_scoreline":"1-3",
    "predicted_advancing_team":"France",
    "advancement_probability_home":0.1830549041,
    "advancement_probability_away":0.8169450959,
    "extra_time_probability":0.1794976886,
    "penalty_shootout_probability":0.0807739599,
    "market_home_win_probability":null,
    "market_draw_probability":null,
    "market_away_win_probability":null,
    "market_90min_home_probability":null,
    "market_90min_draw_probability":null,
    "market_90min_away_probability":null,
    "market_advance_home_probability":null,
    "market_advance_away_probability":null,
    "market_over_2_5_probability":null,
    "market_under_2_5_probability":null,
    "market_btts_yes_probability":null,
    "market_btts_no_probability":null,
    "market_btts_probability":null,
    "home_market_edge":null,
    "draw_market_edge":null,
    "away_market_edge":null,
    "market_disagreement_score":null,
    "market_warning_flag":false,
    "market_warning_reason":null,
    "risk_profile":"aggressive",
    "conservative_scoreline":"0-2",
    "conservative_expected_points":4.2789790759,
    "balanced_scoreline":"1-2",
    "balanced_expected_points":4.332791018,
    "aggressive_scoreline":"1-3",
    "aggressive_expected_points":4.216313843,
    "desperation_scoreline":"2-3",
    "desperation_expected_points":4.2066138152,
    "aggressive_total_goal_cap":4,
    "desperation_total_goal_cap":5,
    "risk_adjusted_candidate_scorelines":"1-2,0-1,0-2,1-3,0-3",
    "recommended_scoreline_by_risk":"1-3",
    "estimated_pick_popularity":0.5105091204,
    "differential_multiplier":1.4160672477,
    "upside_multiplier":1.32,
    "strategic_pick_value":7.8811707995,
    "expected_points_drop_vs_balanced":0.0268827124,
    "strategic_override_allowed":true,
    "strategic_override_reason":"expected-points drop within calibrated risk limit",
    "confidence_level":"high",
    "error_risk":"low",
    "main_reasons":"knockout: clear favorite, late opening risk",
    "alert_flags":"knockout_stage",
    "recommended_pick_type":"aggressive",
    "recommended_pick_explanation":"round_of_16: knockout: clear favorite, late opening risk; risk=aggressive; 90min 1X2 13.2%\/17.9%\/68.9%.",
    "safer_alternative_scoreline":"1-2",
    "safer_alternative_reason":"Higher-probability or lower-variance profile",
    "aggressive_alternative_scoreline":"1-3",
    "aggressive_alternative_reason":"Higher-upside profile within stage-adjusted goal cap",
    "model_warning_summary":null,
    "recommended_home_score":1,
    "recommended_away_score":3,
    "recommended_scoreline":"1-3",
    "recommended_expected_points":4.216313843,
    "draw_alternative_home_score":1,
    "draw_alternative_away_score":1,
    "draw_alternative_scoreline":"1-1",
    "draw_alternative_expected_points":1.4116661839,
    "draw_alternative_is_competitive":false,
    "home_elo":1848.9934444753,
    "away_elo":2122.6630377842,
    "elo_diff":-273.6695933089,
    "same_day_scoreline_count":1,
    "scoreline_diversity_penalty":0.0,
    "diversified_recommended_scoreline":"1-3"
  },
  {
    "date":"2026-07-05",
    "tournament":"FIFA World Cup",
    "home_team":"Brazil",
    "away_team":"Norway",
    "group":null,
    "tournament_stage":"round_of_16",
    "is_group_stage":false,
    "is_knockout_stage":true,
    "is_extra_time_possible":true,
    "is_penalty_possible":true,
    "model_home_expected_goals":2.0095156692,
    "model_away_expected_goals":0.9618298722,
    "context_home_expected_goals":2.0095156692,
    "context_away_expected_goals":0.9618298722,
    "context_home_attack_multiplier":1.0,
    "context_home_defense_multiplier":1.0,
    "context_away_attack_multiplier":1.0,
    "context_away_defense_multiplier":1.0,
    "context_draw_probability_multiplier":1.0,
    "context_applied":false,
    "context_confidence":null,
    "context_notes":null,
    "strategy_home_expected_goals":2.2506575495,
    "strategy_away_expected_goals":1.0772494569,
    "market_adjusted_home_expected_goals":2.2506575495,
    "market_adjusted_away_expected_goals":1.0772494569,
    "home_expected_goals":2.2506575495,
    "away_expected_goals":1.0772494569,
    "goal_inflation":1.4,
    "dynamic_goal_inflation":1.12,
    "stage_adjusted_goal_inflation":1.12,
    "dynamic_goal_inflation_reason":"knockout: clear favorite, late opening risk",
    "inflation_warning_flag":false,
    "inflation_warning_reason":null,
    "max_total_candidate_goals":4,
    "draw_probability_multiplier":1.0,
    "is_last_group_match":false,
    "home_needs_win":false,
    "away_needs_win":false,
    "home_draw_is_enough":false,
    "away_draw_is_enough":false,
    "competitive_context_applied":true,
    "home_already_qualified":false,
    "away_already_qualified":false,
    "home_eliminated":false,
    "away_eliminated":false,
    "home_goal_difference_pressure":false,
    "away_goal_difference_pressure":false,
    "match_pressure_score":1.0,
    "group_scenario_volatility":0.0,
    "home_must_advance":true,
    "away_must_advance":true,
    "knockout_match_importance":1.0,
    "extra_time_risk":0.1937659513,
    "penalty_risk":0.0871946781,
    "knockout_draw_boost":1.0,
    "favorite_caution_factor":0.98,
    "underdog_low_block_factor":1.03,
    "late_game_opening_factor":1.08,
    "home_win_probability":0.6352889126,
    "draw_probability":0.1937659513,
    "away_win_probability":0.1709451361,
    "predicted_90min_scoreline":"3-1",
    "predicted_advancing_team":"Brazil",
    "advancement_probability_home":0.7564180777,
    "advancement_probability_away":0.2435819223,
    "extra_time_probability":0.1937659513,
    "penalty_shootout_probability":0.0871946781,
    "market_home_win_probability":null,
    "market_draw_probability":null,
    "market_away_win_probability":null,
    "market_90min_home_probability":null,
    "market_90min_draw_probability":null,
    "market_90min_away_probability":null,
    "market_advance_home_probability":null,
    "market_advance_away_probability":null,
    "market_over_2_5_probability":null,
    "market_under_2_5_probability":null,
    "market_btts_yes_probability":null,
    "market_btts_no_probability":null,
    "market_btts_probability":null,
    "home_market_edge":null,
    "draw_market_edge":null,
    "away_market_edge":null,
    "market_disagreement_score":null,
    "market_warning_flag":false,
    "market_warning_reason":null,
    "risk_profile":"aggressive",
    "conservative_scoreline":"2-1",
    "conservative_expected_points":4.0612114469,
    "balanced_scoreline":"2-1",
    "balanced_expected_points":4.0612114469,
    "aggressive_scoreline":"3-1",
    "aggressive_expected_points":3.9008649041,
    "desperation_scoreline":"3-2",
    "desperation_expected_points":3.9435754352,
    "aggressive_total_goal_cap":4,
    "desperation_total_goal_cap":5,
    "risk_adjusted_candidate_scorelines":"2-1,1-0,2-0,3-1,3-0",
    "recommended_scoreline_by_risk":"3-1",
    "estimated_pick_popularity":0.5106777915,
    "differential_multiplier":1.4159238772,
    "upside_multiplier":1.32,
    "strategic_pick_value":7.2907926423,
    "expected_points_drop_vs_balanced":0.0394824414,
    "strategic_override_allowed":true,
    "strategic_override_reason":"expected-points drop within calibrated risk limit",
    "confidence_level":"medium",
    "error_risk":"low",
    "main_reasons":"knockout: clear favorite, late opening risk",
    "alert_flags":"knockout_stage",
    "recommended_pick_type":"aggressive",
    "recommended_pick_explanation":"round_of_16: knockout: clear favorite, late opening risk; risk=aggressive; 90min 1X2 63.5%\/19.4%\/17.1%.",
    "safer_alternative_scoreline":"2-1",
    "safer_alternative_reason":"Higher-probability or lower-variance profile",
    "aggressive_alternative_scoreline":"3-1",
    "aggressive_alternative_reason":"Higher-upside profile within stage-adjusted goal cap",
    "model_warning_summary":null,
    "recommended_home_score":3,
    "recommended_away_score":1,
    "recommended_scoreline":"3-1",
    "recommended_expected_points":3.9008649041,
    "draw_alternative_home_score":1,
    "draw_alternative_away_score":1,
    "draw_alternative_scoreline":"1-1",
    "draw_alternative_expected_points":1.5134345872,
    "draw_alternative_is_competitive":false,
    "home_elo":2083.2331464259,
    "away_elo":1929.817356891,
    "elo_diff":153.4157895348,
    "same_day_scoreline_count":1,
    "scoreline_diversity_penalty":0.0,
    "diversified_recommended_scoreline":"3-1"
  },
  {
    "date":"2026-07-05",
    "tournament":"FIFA World Cup",
    "home_team":"Mexico",
    "away_team":"England",
    "group":null,
    "tournament_stage":"round_of_16",
    "is_group_stage":false,
    "is_knockout_stage":true,
    "is_extra_time_possible":true,
    "is_penalty_possible":true,
    "model_home_expected_goals":1.1132961748,
    "model_away_expected_goals":1.0013021509,
    "context_home_expected_goals":1.1132961748,
    "context_away_expected_goals":1.0013021509,
    "context_home_attack_multiplier":1.0,
    "context_home_defense_multiplier":1.0,
    "context_away_attack_multiplier":1.0,
    "context_away_defense_multiplier":1.0,
    "context_draw_probability_multiplier":1.0,
    "context_applied":false,
    "context_confidence":null,
    "context_notes":null,
    "strategy_home_expected_goals":1.2468917158,
    "strategy_away_expected_goals":1.121458409,
    "market_adjusted_home_expected_goals":1.2468917158,
    "market_adjusted_away_expected_goals":1.121458409,
    "home_expected_goals":1.2468917158,
    "away_expected_goals":1.121458409,
    "goal_inflation":1.4,
    "dynamic_goal_inflation":1.12,
    "stage_adjusted_goal_inflation":1.12,
    "dynamic_goal_inflation_reason":"knockout: moderate favorite, controlled tempo",
    "inflation_warning_flag":false,
    "inflation_warning_reason":null,
    "max_total_candidate_goals":4,
    "draw_probability_multiplier":1.04,
    "is_last_group_match":false,
    "home_needs_win":false,
    "away_needs_win":false,
    "home_draw_is_enough":false,
    "away_draw_is_enough":false,
    "competitive_context_applied":true,
    "home_already_qualified":false,
    "away_already_qualified":false,
    "home_eliminated":false,
    "away_eliminated":false,
    "home_goal_difference_pressure":false,
    "away_goal_difference_pressure":false,
    "match_pressure_score":1.0,
    "group_scenario_volatility":0.0,
    "home_must_advance":true,
    "away_must_advance":true,
    "knockout_match_importance":1.0,
    "extra_time_risk":0.2861889493,
    "penalty_risk":0.1287850272,
    "knockout_draw_boost":1.04,
    "favorite_caution_factor":0.96,
    "underdog_low_block_factor":1.06,
    "late_game_opening_factor":1.04,
    "home_win_probability":0.3870865355,
    "draw_probability":0.2861889493,
    "away_win_probability":0.3267245152,
    "predicted_90min_scoreline":"2-1",
    "predicted_advancing_team":"Mexico",
    "advancement_probability_home":0.5086272306,
    "advancement_probability_away":0.4913727694,
    "extra_time_probability":0.2861889493,
    "penalty_shootout_probability":0.1287850272,
    "market_home_win_probability":null,
    "market_draw_probability":null,
    "market_away_win_probability":null,
    "market_90min_home_probability":null,
    "market_90min_draw_probability":null,
    "market_90min_away_probability":null,
    "market_advance_home_probability":null,
    "market_advance_away_probability":null,
    "market_over_2_5_probability":null,
    "market_under_2_5_probability":null,
    "market_btts_yes_probability":null,
    "market_btts_no_probability":null,
    "market_btts_probability":null,
    "home_market_edge":null,
    "draw_market_edge":null,
    "away_market_edge":null,
    "market_disagreement_score":null,
    "market_warning_flag":false,
    "market_warning_reason":null,
    "risk_profile":"aggressive",
    "conservative_scoreline":"1-0",
    "conservative_expected_points":2.8188951883,
    "balanced_scoreline":"1-0",
    "balanced_expected_points":2.8188951883,
    "aggressive_scoreline":"2-1",
    "aggressive_expected_points":2.749389032,
    "desperation_scoreline":"3-1",
    "desperation_expected_points":2.3386939846,
    "aggressive_total_goal_cap":4,
    "desperation_total_goal_cap":4,
    "risk_adjusted_candidate_scorelines":"1-0,2-1",
    "recommended_scoreline_by_risk":"2-1",
    "estimated_pick_popularity":0.5016212732,
    "differential_multiplier":1.4236219177,
    "upside_multiplier":1.22,
    "strategic_pick_value":4.7751903934,
    "expected_points_drop_vs_balanced":0.0246572333,
    "strategic_override_allowed":true,
    "strategic_override_reason":"expected-points drop within calibrated risk limit",
    "confidence_level":"low",
    "error_risk":"high",
    "main_reasons":"knockout: moderate favorite, controlled tempo",
    "alert_flags":"knockout_stage",
    "recommended_pick_type":"aggressive",
    "recommended_pick_explanation":"round_of_16: knockout: moderate favorite, controlled tempo; risk=aggressive; 90min 1X2 38.7%\/28.6%\/32.7%.",
    "safer_alternative_scoreline":"1-0",
    "safer_alternative_reason":"Higher-probability or lower-variance profile",
    "aggressive_alternative_scoreline":"2-1",
    "aggressive_alternative_reason":"Higher-upside profile within stage-adjusted goal cap",
    "model_warning_summary":null,
    "recommended_home_score":2,
    "recommended_away_score":1,
    "recommended_scoreline":"2-1",
    "recommended_expected_points":2.749389032,
    "draw_alternative_home_score":1,
    "draw_alternative_away_score":1,
    "draw_alternative_scoreline":"1-1",
    "draw_alternative_expected_points":2.2560813853,
    "draw_alternative_is_competitive":false,
    "home_elo":1976.7144111761,
    "away_elo":2067.7830892798,
    "elo_diff":-91.0686781037,
    "same_day_scoreline_count":1,
    "scoreline_diversity_penalty":0.0,
    "diversified_recommended_scoreline":"2-1"
  },
  {
    "date":"2026-07-06",
    "tournament":"FIFA World Cup",
    "home_team":"United States",
    "away_team":"Belgium",
    "group":null,
    "tournament_stage":"round_of_16",
    "is_group_stage":false,
    "is_knockout_stage":true,
    "is_extra_time_possible":true,
    "is_penalty_possible":true,
    "model_home_expected_goals":1.3113771073,
    "model_away_expected_goals":1.4947169469,
    "context_home_expected_goals":1.3113771073,
    "context_away_expected_goals":1.4947169469,
    "context_home_attack_multiplier":1.0,
    "context_home_defense_multiplier":1.0,
    "context_away_attack_multiplier":1.0,
    "context_away_defense_multiplier":1.0,
    "context_draw_probability_multiplier":1.0,
    "context_applied":false,
    "context_confidence":null,
    "context_notes":null,
    "strategy_home_expected_goals":1.4687423602,
    "strategy_away_expected_goals":1.6740829805,
    "market_adjusted_home_expected_goals":1.4687423602,
    "market_adjusted_away_expected_goals":1.6740829805,
    "home_expected_goals":1.4687423602,
    "away_expected_goals":1.6740829805,
    "goal_inflation":1.4,
    "dynamic_goal_inflation":1.12,
    "stage_adjusted_goal_inflation":1.12,
    "dynamic_goal_inflation_reason":"knockout: moderate favorite, controlled tempo",
    "inflation_warning_flag":false,
    "inflation_warning_reason":null,
    "max_total_candidate_goals":4,
    "draw_probability_multiplier":1.04,
    "is_last_group_match":false,
    "home_needs_win":false,
    "away_needs_win":false,
    "home_draw_is_enough":false,
    "away_draw_is_enough":false,
    "competitive_context_applied":true,
    "home_already_qualified":false,
    "away_already_qualified":false,
    "home_eliminated":false,
    "away_eliminated":false,
    "home_goal_difference_pressure":false,
    "away_goal_difference_pressure":false,
    "match_pressure_score":1.0,
    "group_scenario_volatility":0.0,
    "home_must_advance":true,
    "away_must_advance":true,
    "knockout_match_importance":1.0,
    "extra_time_risk":0.2431099099,
    "penalty_risk":0.1093994595,
    "knockout_draw_boost":1.04,
    "favorite_caution_factor":0.96,
    "underdog_low_block_factor":1.06,
    "late_game_opening_factor":1.04,
    "home_win_probability":0.3350404167,
    "draw_probability":0.2431099099,
    "away_win_probability":0.4218496734,
    "predicted_90min_scoreline":"1-2",
    "predicted_advancing_team":"Belgium",
    "advancement_probability_home":0.4375392551,
    "advancement_probability_away":0.5624607449,
    "extra_time_probability":0.2431099099,
    "penalty_shootout_probability":0.1093994595,
    "market_home_win_probability":null,
    "market_draw_probability":null,
    "market_away_win_probability":null,
    "market_90min_home_probability":null,
    "market_90min_draw_probability":null,
    "market_90min_away_probability":null,
    "market_advance_home_probability":null,
    "market_advance_away_probability":null,
    "market_over_2_5_probability":null,
    "market_under_2_5_probability":null,
    "market_btts_yes_probability":null,
    "market_btts_no_probability":null,
    "market_btts_probability":null,
    "home_market_edge":null,
    "draw_market_edge":null,
    "away_market_edge":null,
    "market_disagreement_score":null,
    "market_warning_flag":false,
    "market_warning_reason":null,
    "risk_profile":"aggressive",
    "conservative_scoreline":"1-2",
    "conservative_expected_points":2.8992895096,
    "balanced_scoreline":"1-2",
    "balanced_expected_points":2.8992895096,
    "aggressive_scoreline":"1-2",
    "aggressive_expected_points":2.8992895096,
    "desperation_scoreline":"1-3",
    "desperation_expected_points":2.589201372,
    "aggressive_total_goal_cap":4,
    "desperation_total_goal_cap":4,
    "risk_adjusted_candidate_scorelines":"1-2,0-1,0-2",
    "recommended_scoreline_by_risk":"1-2",
    "estimated_pick_popularity":0.5831224958,
    "differential_multiplier":1.3543458786,
    "upside_multiplier":1.22,
    "strategic_pick_value":4.7905017738,
    "expected_points_drop_vs_balanced":0.0,
    "strategic_override_allowed":true,
    "strategic_override_reason":"expected-points drop within calibrated risk limit",
    "confidence_level":"low",
    "error_risk":"high",
    "main_reasons":"knockout: moderate favorite, controlled tempo",
    "alert_flags":"knockout_stage",
    "recommended_pick_type":"aggressive",
    "recommended_pick_explanation":"round_of_16: knockout: moderate favorite, controlled tempo; risk=aggressive; 90min 1X2 33.5%\/24.3%\/42.2%.",
    "safer_alternative_scoreline":"1-2",
    "safer_alternative_reason":"Higher-probability or lower-variance profile",
    "aggressive_alternative_scoreline":"1-2",
    "aggressive_alternative_reason":"Higher-upside profile within stage-adjusted goal cap",
    "model_warning_summary":null,
    "recommended_home_score":1,
    "recommended_away_score":2,
    "recommended_scoreline":"1-2",
    "recommended_expected_points":2.8992895096,
    "draw_alternative_home_score":1,
    "draw_alternative_away_score":1,
    "draw_alternative_scoreline":"1-1",
    "draw_alternative_expected_points":1.8971186285,
    "draw_alternative_is_competitive":false,
    "home_elo":1881.3456154467,
    "away_elo":1976.1894920258,
    "elo_diff":-94.8438765792,
    "same_day_scoreline_count":1,
    "scoreline_diversity_penalty":0.0,
    "diversified_recommended_scoreline":"1-2"
  }
]