[
  {
    "date":"2026-06-19",
    "tournament":"FIFA World Cup",
    "home_team":"Brazil",
    "away_team":"Haiti",
    "model_home_expected_goals":2.7562646112,
    "model_away_expected_goals":0.6449341715,
    "home_expected_goals":3.8587704557,
    "away_expected_goals":0.9029078401,
    "goal_inflation":1.4,
    "max_total_candidate_goals":4,
    "draw_probability_multiplier":1.0,
    "home_win_probability":0.8658659366,
    "draw_probability":0.0850758853,
    "away_win_probability":0.0490581781,
    "recommended_home_score":3,
    "recommended_away_score":0,
    "recommended_scoreline":"3-0",
    "recommended_expected_points":5.1178528064,
    "draw_alternative_home_score":1,
    "draw_alternative_away_score":1,
    "draw_alternative_scoreline":"1-1",
    "draw_alternative_expected_points":0.642361448,
    "draw_alternative_is_competitive":false,
    "home_elo":2058.7190050449,
    "away_elo":1677.6194333715,
    "elo_diff":381.0995716734
  },
  {
    "date":"2026-06-19",
    "tournament":"FIFA World Cup",
    "home_team":"Scotland",
    "away_team":"Morocco",
    "model_home_expected_goals":0.8858744148,
    "model_away_expected_goals":1.7611117155,
    "home_expected_goals":1.2402241807,
    "away_expected_goals":2.4655564017,
    "goal_inflation":1.4,
    "max_total_candidate_goals":4,
    "draw_probability_multiplier":1.0,
    "home_win_probability":0.1788214721,
    "draw_probability":0.1834417998,
    "away_win_probability":0.6377367281,
    "recommended_home_score":1,
    "recommended_away_score":2,
    "recommended_scoreline":"1-2",
    "recommended_expected_points":4.0290546838,
    "draw_alternative_home_score":1,
    "draw_alternative_away_score":1,
    "draw_alternative_scoreline":"1-1",
    "draw_alternative_expected_points":1.4054412366,
    "draw_alternative_is_competitive":false,
    "home_elo":1815.073739299,
    "away_elo":1964.4131860426,
    "elo_diff":-149.3394467436
  },
  {
    "date":"2026-06-19",
    "tournament":"FIFA World Cup",
    "home_team":"Turkey",
    "away_team":"Paraguay",
    "model_home_expected_goals":1.379789425,
    "model_away_expected_goals":1.2125315548,
    "home_expected_goals":1.931705195,
    "away_expected_goals":1.6975441768,
    "goal_inflation":1.4,
    "max_total_candidate_goals":4,
    "draw_probability_multiplier":1.0,
    "home_win_probability":0.4373584035,
    "draw_probability":0.2181929017,
    "away_win_probability":0.3444486948,
    "recommended_home_score":2,
    "recommended_away_score":1,
    "recommended_scoreline":"2-1",
    "recommended_expected_points":2.9473703411,
    "draw_alternative_home_score":1,
    "draw_alternative_away_score":1,
    "draw_alternative_scoreline":"1-1",
    "draw_alternative_expected_points":1.6591883973,
    "draw_alternative_is_competitive":false,
    "home_elo":1875.0970381561,
    "away_elo":1828.0933308282,
    "elo_diff":47.0037073279
  },
  {
    "date":"2026-06-19",
    "tournament":"FIFA World Cup",
    "home_team":"United States",
    "away_team":"Australia",
    "model_home_expected_goals":1.3109357844,
    "model_away_expected_goals":1.148105018,
    "home_expected_goals":1.8353100982,
    "away_expected_goals":1.6073470252,
    "goal_inflation":1.4,
    "max_total_candidate_goals":4,
    "draw_probability_multiplier":1.0,
    "home_win_probability":0.4342817988,
    "draw_probability":0.2243874648,
    "away_win_probability":0.3413307363,
    "recommended_home_score":2,
    "recommended_away_score":1,
    "recommended_scoreline":"2-1",
    "recommended_expected_points":2.9477865999,
    "draw_alternative_home_score":1,
    "draw_alternative_away_score":1,
    "draw_alternative_scoreline":"1-1",
    "draw_alternative_expected_points":1.7252820481,
    "draw_alternative_is_competitive":false,
    "home_elo":1870.2654488243,
    "away_elo":1911.6698743289,
    "elo_diff":-41.4044255047
  },
  {
    "date":"2026-06-20",
    "tournament":"FIFA World Cup",
    "home_team":"Germany",
    "away_team":"Ivory Coast",
    "model_home_expected_goals":2.0038670049,
    "model_away_expected_goals":0.9302811434,
    "home_expected_goals":2.8054138069,
    "away_expected_goals":1.3023936008,
    "goal_inflation":1.4,
    "max_total_candidate_goals":4,
    "draw_probability_multiplier":1.0,
    "home_win_probability":0.6796096704,
    "draw_probability":0.1636902369,
    "away_win_probability":0.1567000927,
    "recommended_home_score":2,
    "recommended_away_score":1,
    "recommended_scoreline":"2-1",
    "recommended_expected_points":4.1880497901,
    "draw_alternative_home_score":1,
    "draw_alternative_away_score":1,
    "draw_alternative_scoreline":"1-1",
    "draw_alternative_expected_points":1.2286372865,
    "draw_alternative_is_competitive":false,
    "home_elo":1998.3284782599,
    "away_elo":1813.3199286567,
    "elo_diff":185.0085496032
  },
  {
    "date":"2026-06-20",
    "tournament":"FIFA World Cup",
    "home_team":"Ecuador",
    "away_team":"Curaçao",
    "model_home_expected_goals":3.0248622916,
    "model_away_expected_goals":0.5482905587,
    "home_expected_goals":4.2348072083,
    "away_expected_goals":0.7676067822,
    "goal_inflation":1.4,
    "max_total_candidate_goals":4,
    "draw_probability_multiplier":1.0,
    "home_win_probability":0.9070431952,
    "draw_probability":0.0628064619,
    "away_win_probability":0.0301503428,
    "recommended_home_score":3,
    "recommended_away_score":0,
    "recommended_scoreline":"3-0",
    "recommended_expected_points":5.3603224529,
    "draw_alternative_home_score":1,
    "draw_alternative_away_score":1,
    "draw_alternative_scoreline":"1-1",
    "draw_alternative_expected_points":0.4780616663,
    "draw_alternative_is_competitive":false,
    "home_elo":1947.6143635162,
    "away_elo":1579.4336743672,
    "elo_diff":368.180689149
  },
  {
    "date":"2026-06-20",
    "tournament":"FIFA World Cup",
    "home_team":"Netherlands",
    "away_team":"Sweden",
    "model_home_expected_goals":2.2218628452,
    "model_away_expected_goals":0.8415220944,
    "home_expected_goals":3.1106079833,
    "away_expected_goals":1.1781309322,
    "goal_inflation":1.4,
    "max_total_candidate_goals":4,
    "draw_probability_multiplier":1.0,
    "home_win_probability":0.7462836317,
    "draw_probability":0.1393538957,
    "away_win_probability":0.1143624726,
    "recommended_home_score":3,
    "recommended_away_score":1,
    "recommended_scoreline":"3-1",
    "recommended_expected_points":4.5097275251,
    "draw_alternative_home_score":1,
    "draw_alternative_away_score":1,
    "draw_alternative_scoreline":"1-1",
    "draw_alternative_expected_points":1.0455715553,
    "draw_alternative_is_competitive":false,
    "home_elo":1996.0597382435,
    "away_elo":1785.2169769885,
    "elo_diff":210.8427612549
  },
  {
    "date":"2026-06-20",
    "tournament":"FIFA World Cup",
    "home_team":"Tunisia",
    "away_team":"Japan",
    "model_home_expected_goals":0.7382894784,
    "model_away_expected_goals":2.0022694043,
    "home_expected_goals":1.0336052697,
    "away_expected_goals":2.803177166,
    "goal_inflation":1.4,
    "max_total_candidate_goals":4,
    "draw_probability_multiplier":1.0,
    "home_win_probability":0.1148260172,
    "draw_probability":0.1505391149,
    "away_win_probability":0.7346348679,
    "recommended_home_score":1,
    "recommended_away_score":2,
    "recommended_scoreline":"1-2",
    "recommended_expected_points":4.4744269868,
    "draw_alternative_home_score":1,
    "draw_alternative_away_score":1,
    "draw_alternative_scoreline":"1-1",
    "draw_alternative_expected_points":1.1594509477,
    "draw_alternative_is_competitive":false,
    "home_elo":1723.2682748016,
    "away_elo":1984.6863732384,
    "elo_diff":-261.4180984368
  },
  {
    "date":"2026-06-21",
    "tournament":"FIFA World Cup",
    "home_team":"Spain",
    "away_team":"Saudi Arabia",
    "model_home_expected_goals":2.9639253376,
    "model_away_expected_goals":0.5141627503,
    "home_expected_goals":4.1494954727,
    "away_expected_goals":0.7198278505,
    "goal_inflation":1.4,
    "max_total_candidate_goals":4,
    "draw_probability_multiplier":1.0,
    "home_win_probability":0.9087140744,
    "draw_probability":0.0625569807,
    "away_win_probability":0.0287289449,
    "recommended_home_score":3,
    "recommended_away_score":0,
    "recommended_scoreline":"3-0",
    "recommended_expected_points":5.383438994,
    "draw_alternative_home_score":1,
    "draw_alternative_away_score":1,
    "draw_alternative_scoreline":"1-1",
    "draw_alternative_expected_points":0.4804090621,
    "draw_alternative_is_competitive":false,
    "home_elo":2144.9255019351,
    "away_elo":1698.0976722276,
    "elo_diff":446.8278297076
  },
  {
    "date":"2026-06-21",
    "tournament":"FIFA World Cup",
    "home_team":"Uruguay",
    "away_team":"Cape Verde",
    "model_home_expected_goals":2.1957672786,
    "model_away_expected_goals":0.6242195191,
    "home_expected_goals":3.07407419,
    "away_expected_goals":0.8739073268,
    "goal_inflation":1.4,
    "max_total_candidate_goals":4,
    "draw_probability_multiplier":1.0,
    "home_win_probability":0.8004473411,
    "draw_probability":0.1228700889,
    "away_win_probability":0.07668257,
    "recommended_home_score":2,
    "recommended_away_score":0,
    "recommended_scoreline":"2-0",
    "recommended_expected_points":4.8326346799,
    "draw_alternative_home_score":1,
    "draw_alternative_away_score":1,
    "draw_alternative_scoreline":"1-1",
    "draw_alternative_expected_points":0.9526052227,
    "draw_alternative_is_competitive":false,
    "home_elo":1943.8793757479,
    "away_elo":1641.479438499,
    "elo_diff":302.3999372489
  },
  {
    "date":"2026-06-21",
    "tournament":"FIFA World Cup",
    "home_team":"Belgium",
    "away_team":"Iran",
    "model_home_expected_goals":1.5821705394,
    "model_away_expected_goals":1.1729211477,
    "home_expected_goals":2.2150387552,
    "away_expected_goals":1.6420896068,
    "goal_inflation":1.4,
    "max_total_candidate_goals":4,
    "draw_probability_multiplier":1.0,
    "home_win_probability":0.5063712234,
    "draw_probability":0.2054556695,
    "away_win_probability":0.2881731072,
    "recommended_home_score":2,
    "recommended_away_score":1,
    "recommended_scoreline":"2-1",
    "recommended_expected_points":3.3163700535,
    "draw_alternative_home_score":1,
    "draw_alternative_away_score":1,
    "draw_alternative_scoreline":"1-1",
    "draw_alternative_expected_points":1.5430107782,
    "draw_alternative_is_competitive":false,
    "home_elo":1957.2799795586,
    "away_elo":1893.4474460293,
    "elo_diff":63.8325335293
  },
  {
    "date":"2026-06-21",
    "tournament":"FIFA World Cup",
    "home_team":"New Zealand",
    "away_team":"Egypt",
    "model_home_expected_goals":1.1027558304,
    "model_away_expected_goals":1.356156214,
    "home_expected_goals":1.5438581626,
    "away_expected_goals":1.8986186996,
    "goal_inflation":1.4,
    "max_total_candidate_goals":4,
    "draw_probability_multiplier":1.0,
    "home_win_probability":0.3166351227,
    "draw_probability":0.2224453939,
    "away_win_probability":0.4609194834,
    "recommended_home_score":1,
    "recommended_away_score":2,
    "recommended_scoreline":"1-2",
    "recommended_expected_points":3.1028356107,
    "draw_alternative_home_score":1,
    "draw_alternative_away_score":1,
    "draw_alternative_scoreline":"1-1",
    "draw_alternative_expected_points":1.7113969791,
    "draw_alternative_is_competitive":false,
    "home_elo":1728.972016488,
    "away_elo":1782.0685106616,
    "elo_diff":-53.0964941736
  },
  {
    "date":"2026-06-22",
    "tournament":"FIFA World Cup",
    "home_team":"France",
    "away_team":"Iraq",
    "model_home_expected_goals":2.6982823737,
    "model_away_expected_goals":0.6058817679,
    "home_expected_goals":3.7775953232,
    "away_expected_goals":0.848234475,
    "goal_inflation":1.4,
    "max_total_candidate_goals":4,
    "draw_probability_multiplier":1.0,
    "home_win_probability":0.8683150677,
    "draw_probability":0.0848607746,
    "away_win_probability":0.0468241577,
    "recommended_home_score":3,
    "recommended_away_score":0,
    "recommended_scoreline":"3-0",
    "recommended_expected_points":5.1442627174,
    "draw_alternative_home_score":1,
    "draw_alternative_away_score":1,
    "draw_alternative_scoreline":"1-1",
    "draw_alternative_expected_points":0.646956351,
    "draw_alternative_is_competitive":false,
    "home_elo":2096.5675872274,
    "away_elo":1703.2404079939,
    "elo_diff":393.3271792336
  },
  {
    "date":"2026-06-22",
    "tournament":"FIFA World Cup",
    "home_team":"Norway",
    "away_team":"Senegal",
    "model_home_expected_goals":1.7057074729,
    "model_away_expected_goals":1.1499496846,
    "home_expected_goals":2.387990462,
    "away_expected_goals":1.6099295584,
    "goal_inflation":1.4,
    "max_total_candidate_goals":4,
    "draw_probability_multiplier":1.0,
    "home_win_probability":0.5459304502,
    "draw_probability":0.1963363469,
    "away_win_probability":0.2577332029,
    "recommended_home_score":2,
    "recommended_away_score":1,
    "recommended_scoreline":"2-1",
    "recommended_expected_points":3.5174553942,
    "draw_alternative_home_score":1,
    "draw_alternative_away_score":1,
    "draw_alternative_scoreline":"1-1",
    "draw_alternative_expected_points":1.4638855314,
    "draw_alternative_is_competitive":false,
    "home_elo":1924.9498446916,
    "away_elo":1871.5491482862,
    "elo_diff":53.4006964054
  },
  {
    "date":"2026-06-22",
    "tournament":"FIFA World Cup",
    "home_team":"Argentina",
    "away_team":"Austria",
    "model_home_expected_goals":2.2936698106,
    "model_away_expected_goals":0.7349572153,
    "home_expected_goals":3.2111377348,
    "away_expected_goals":1.0289401015,
    "goal_inflation":1.4,
    "max_total_candidate_goals":4,
    "draw_probability_multiplier":1.0,
    "home_win_probability":0.786482771,
    "draw_probability":0.1248370944,
    "away_win_probability":0.0886801346,
    "recommended_home_score":3,
    "recommended_away_score":1,
    "recommended_scoreline":"3-1",
    "recommended_expected_points":4.7270892241,
    "draw_alternative_home_score":1,
    "draw_alternative_away_score":1,
    "draw_alternative_scoreline":"1-1",
    "draw_alternative_expected_points":0.9484764505,
    "draw_alternative_is_competitive":false,
    "home_elo":2157.4074030027,
    "away_elo":1884.1524680474,
    "elo_diff":273.2549349554
  },
  {
    "date":"2026-06-22",
    "tournament":"FIFA World Cup",
    "home_team":"Jordan",
    "away_team":"Algeria",
    "model_home_expected_goals":0.9755796449,
    "model_away_expected_goals":1.7147201994,
    "home_expected_goals":1.3658115029,
    "away_expected_goals":2.4006082792,
    "goal_inflation":1.4,
    "max_total_candidate_goals":4,
    "draw_probability_multiplier":1.0,
    "home_win_probability":0.2093964765,
    "draw_probability":0.191447394,
    "away_win_probability":0.5991561295,
    "recommended_home_score":1,
    "recommended_away_score":2,
    "recommended_scoreline":"1-2",
    "recommended_expected_points":3.8251625549,
    "draw_alternative_home_score":1,
    "draw_alternative_away_score":1,
    "draw_alternative_scoreline":"1-1",
    "draw_alternative_expected_points":1.4558283132,
    "draw_alternative_is_competitive":false,
    "home_elo":1744.4625195924,
    "away_elo":1866.7300590439,
    "elo_diff":-122.2675394515
  },
  {
    "date":"2026-06-23",
    "tournament":"FIFA World Cup",
    "home_team":"Portugal",
    "away_team":"Uzbekistan",
    "model_home_expected_goals":1.9311100155,
    "model_away_expected_goals":0.830695876,
    "home_expected_goals":2.7035540217,
    "away_expected_goals":1.1629742264,
    "goal_inflation":1.4,
    "max_total_candidate_goals":4,
    "draw_probability_multiplier":1.0,
    "home_win_probability":0.6930811066,
    "draw_probability":0.164007452,
    "away_win_probability":0.1429114414,
    "recommended_home_score":2,
    "recommended_away_score":1,
    "recommended_scoreline":"2-1",
    "recommended_expected_points":4.2798579631,
    "draw_alternative_home_score":1,
    "draw_alternative_away_score":1,
    "draw_alternative_scoreline":"1-1",
    "draw_alternative_expected_points":1.2529052958,
    "draw_alternative_is_competitive":false,
    "home_elo":2019.7122644869,
    "away_elo":1802.2580019002,
    "elo_diff":217.4542625867
  },
  {
    "date":"2026-06-23",
    "tournament":"FIFA World Cup",
    "home_team":"Colombia",
    "away_team":"DR Congo",
    "model_home_expected_goals":2.155558846,
    "model_away_expected_goals":0.7151750787,
    "home_expected_goals":3.0177823844,
    "away_expected_goals":1.0012451102,
    "goal_inflation":1.4,
    "max_total_candidate_goals":4,
    "draw_probability_multiplier":1.0,
    "home_win_probability":0.7692228143,
    "draw_probability":0.1346406267,
    "away_win_probability":0.0961365589,
    "recommended_home_score":3,
    "recommended_away_score":1,
    "recommended_scoreline":"3-1",
    "recommended_expected_points":4.6458273844,
    "draw_alternative_home_score":1,
    "draw_alternative_away_score":1,
    "draw_alternative_scoreline":"1-1",
    "draw_alternative_expected_points":1.0327967862,
    "draw_alternative_is_competitive":false,
    "home_elo":2042.4549771892,
    "away_elo":1728.3589327918,
    "elo_diff":314.0960443974
  },
  {
    "date":"2026-06-23",
    "tournament":"FIFA World Cup",
    "home_team":"England",
    "away_team":"Ghana",
    "model_home_expected_goals":2.7846131012,
    "model_away_expected_goals":0.543599018,
    "home_expected_goals":3.8984583417,
    "away_expected_goals":0.7610386253,
    "goal_inflation":1.4,
    "max_total_candidate_goals":4,
    "draw_probability_multiplier":1.0,
    "home_win_probability":0.889100035,
    "draw_probability":0.0741666001,
    "away_win_probability":0.0367333649,
    "recommended_home_score":3,
    "recommended_away_score":0,
    "recommended_scoreline":"3-0",
    "recommended_expected_points":5.2765860492,
    "draw_alternative_home_score":1,
    "draw_alternative_away_score":1,
    "draw_alternative_scoreline":"1-1",
    "draw_alternative_expected_points":0.5699408262,
    "draw_alternative_is_competitive":false,
    "home_elo":2067.3089633583,
    "away_elo":1653.2031236897,
    "elo_diff":414.1058396686
  },
  {
    "date":"2026-06-23",
    "tournament":"FIFA World Cup",
    "home_team":"Panama",
    "away_team":"Croatia",
    "model_home_expected_goals":1.0618846269,
    "model_away_expected_goals":1.7317857795,
    "home_expected_goals":1.4866384776,
    "away_expected_goals":2.4245000913,
    "goal_inflation":1.4,
    "max_total_candidate_goals":4,
    "draw_probability_multiplier":1.0,
    "home_win_probability":0.2294609418,
    "draw_probability":0.1925311305,
    "away_win_probability":0.5780079276,
    "recommended_home_score":1,
    "recommended_away_score":2,
    "recommended_scoreline":"1-2",
    "recommended_expected_points":3.6980490617,
    "draw_alternative_home_score":1,
    "draw_alternative_away_score":1,
    "draw_alternative_scoreline":"1-1",
    "draw_alternative_expected_points":1.4476105405,
    "draw_alternative_is_competitive":false,
    "home_elo":1793.5538470601,
    "away_elo":1931.7111995508,
    "elo_diff":-138.1573524906
  },
  {
    "date":"2026-06-24",
    "tournament":"FIFA World Cup",
    "home_team":"Canada",
    "away_team":"Switzerland",
    "model_home_expected_goals":1.3911598898,
    "model_away_expected_goals":0.9161171409,
    "home_expected_goals":1.9476238457,
    "away_expected_goals":1.2825639973,
    "goal_inflation":1.4,
    "max_total_candidate_goals":4,
    "draw_probability_multiplier":1.0,
    "home_win_probability":0.5274471244,
    "draw_probability":0.2210749841,
    "away_win_probability":0.2514778915,
    "recommended_home_score":2,
    "recommended_away_score":1,
    "recommended_scoreline":"2-1",
    "recommended_expected_points":3.5016367815,
    "draw_alternative_home_score":1,
    "draw_alternative_away_score":1,
    "draw_alternative_scoreline":"1-1",
    "draw_alternative_expected_points":1.723336126,
    "draw_alternative_is_competitive":false,
    "home_elo":1880.0133401219,
    "away_elo":1923.8882725558,
    "elo_diff":-43.8749324339
  },
  {
    "date":"2026-06-24",
    "tournament":"FIFA World Cup",
    "home_team":"Morocco",
    "away_team":"Haiti",
    "model_home_expected_goals":2.2054199887,
    "model_away_expected_goals":0.6643711544,
    "home_expected_goals":3.0875879841,
    "away_expected_goals":0.9301196162,
    "goal_inflation":1.4,
    "max_total_candidate_goals":4,
    "draw_probability_multiplier":1.0,
    "home_win_probability":0.7912381931,
    "draw_probability":0.125800501,
    "away_win_probability":0.0829613059,
    "recommended_home_score":2,
    "recommended_away_score":0,
    "recommended_scoreline":"2-0",
    "recommended_expected_points":4.7697990184,
    "draw_alternative_home_score":1,
    "draw_alternative_away_score":1,
    "draw_alternative_scoreline":"1-1",
    "draw_alternative_expected_points":0.9697105496,
    "draw_alternative_is_competitive":false,
    "home_elo":1964.4131860426,
    "away_elo":1677.6194333715,
    "elo_diff":286.7937526711
  },
  {
    "date":"2026-06-24",
    "tournament":"FIFA World Cup",
    "home_team":"South Africa",
    "away_team":"South Korea",
    "model_home_expected_goals":0.8374644877,
    "model_away_expected_goals":1.6247569755,
    "home_expected_goals":1.1724502828,
    "away_expected_goals":2.2746597657,
    "goal_inflation":1.4,
    "max_total_candidate_goals":4,
    "draw_probability_multiplier":1.0,
    "home_win_probability":0.1867586022,
    "draw_probability":0.1950167545,
    "away_win_probability":0.6182246433,
    "recommended_home_score":1,
    "recommended_away_score":2,
    "recommended_scoreline":"1-2",
    "recommended_expected_points":3.9606538567,
    "draw_alternative_home_score":1,
    "draw_alternative_away_score":1,
    "draw_alternative_scoreline":"1-1",
    "draw_alternative_expected_points":1.5128411645,
    "draw_alternative_is_competitive":false,
    "home_elo":1664.33628409,
    "away_elo":1877.2114096749,
    "elo_diff":-212.8751255849
  },
  {
    "date":"2026-06-24",
    "tournament":"FIFA World Cup",
    "home_team":"Scotland",
    "away_team":"Brazil",
    "model_home_expected_goals":0.8247412256,
    "model_away_expected_goals":2.2072929205,
    "home_expected_goals":1.1546377158,
    "away_expected_goals":3.0902100887,
    "goal_inflation":1.4,
    "max_total_candidate_goals":4,
    "draw_probability_multiplier":1.0,
    "home_win_probability":0.1124696555,
    "draw_probability":0.1392452232,
    "away_win_probability":0.7482851213,
    "recommended_home_score":1,
    "recommended_away_score":3,
    "recommended_scoreline":"1-3",
    "recommended_expected_points":4.5226719653,
    "draw_alternative_home_score":1,
    "draw_alternative_away_score":1,
    "draw_alternative_scoreline":"1-1",
    "draw_alternative_expected_points":1.0482901708,
    "draw_alternative_is_competitive":false,
    "home_elo":1815.073739299,
    "away_elo":2058.7190050449,
    "elo_diff":-243.6452657459
  },
  {
    "date":"2026-06-24",
    "tournament":"FIFA World Cup",
    "home_team":"Bosnia and Herzegovina",
    "away_team":"Qatar",
    "model_home_expected_goals":1.3607895383,
    "model_away_expected_goals":1.0666837556,
    "home_expected_goals":1.9051053536,
    "away_expected_goals":1.4933572579,
    "goal_inflation":1.4,
    "max_total_candidate_goals":4,
    "draw_probability_multiplier":1.0,
    "home_win_probability":0.4727552797,
    "draw_probability":0.2227808486,
    "away_win_probability":0.3044638718,
    "recommended_home_score":2,
    "recommended_away_score":1,
    "recommended_scoreline":"2-1",
    "recommended_expected_points":3.1754410044,
    "draw_alternative_home_score":1,
    "draw_alternative_away_score":1,
    "draw_alternative_scoreline":"1-1",
    "draw_alternative_expected_points":1.7187370961,
    "draw_alternative_is_competitive":false,
    "home_elo":1625.2982974123,
    "away_elo":1588.2797233274,
    "elo_diff":37.0185740848
  },
  {
    "date":"2026-06-24",
    "tournament":"FIFA World Cup",
    "home_team":"Mexico",
    "away_team":"Czech Republic",
    "model_home_expected_goals":1.9877234772,
    "model_away_expected_goals":0.6470215606,
    "home_expected_goals":2.782812868,
    "away_expected_goals":0.9058301849,
    "goal_inflation":1.4,
    "max_total_candidate_goals":4,
    "draw_probability_multiplier":1.0,
    "home_win_probability":0.7583291109,
    "draw_probability":0.1442585866,
    "away_win_probability":0.0974123025,
    "recommended_home_score":2,
    "recommended_away_score":0,
    "recommended_scoreline":"2-0",
    "recommended_expected_points":4.6309610338,
    "draw_alternative_home_score":1,
    "draw_alternative_away_score":1,
    "draw_alternative_scoreline":"1-1",
    "draw_alternative_expected_points":1.1238237902,
    "draw_alternative_is_competitive":false,
    "home_elo":1948.9168005718,
    "away_elo":1771.5371179075,
    "elo_diff":177.3796826643
  },
  {
    "date":"2026-06-25",
    "tournament":"FIFA World Cup",
    "home_team":"Curaçao",
    "away_team":"Ivory Coast",
    "model_home_expected_goals":0.8434210825,
    "model_away_expected_goals":2.2275236579,
    "home_expected_goals":1.1807895155,
    "away_expected_goals":3.1185331211,
    "goal_inflation":1.4,
    "max_total_candidate_goals":4,
    "draw_probability_multiplier":1.0,
    "home_win_probability":0.1142013471,
    "draw_probability":0.139042497,
    "away_win_probability":0.7467561559,
    "recommended_home_score":1,
    "recommended_away_score":3,
    "recommended_scoreline":"1-3",
    "recommended_expected_points":4.5118139868,
    "draw_alternative_home_score":1,
    "draw_alternative_away_score":1,
    "draw_alternative_scoreline":"1-1",
    "draw_alternative_expected_points":1.0425923647,
    "draw_alternative_is_competitive":false,
    "home_elo":1579.4336743672,
    "away_elo":1813.3199286567,
    "elo_diff":-233.8862542895
  },
  {
    "date":"2026-06-25",
    "tournament":"FIFA World Cup",
    "home_team":"Paraguay",
    "away_team":"Australia",
    "model_home_expected_goals":1.0296175418,
    "model_away_expected_goals":1.4114071346,
    "home_expected_goals":1.4414645585,
    "away_expected_goals":1.9759699885,
    "goal_inflation":1.4,
    "max_total_candidate_goals":4,
    "draw_probability_multiplier":1.0,
    "home_win_probability":0.2819734696,
    "draw_probability":0.2190794278,
    "away_win_probability":0.4989471027,
    "recommended_home_score":1,
    "recommended_away_score":2,
    "recommended_scoreline":"1-2",
    "recommended_expected_points":3.3222315194,
    "draw_alternative_home_score":1,
    "draw_alternative_away_score":1,
    "draw_alternative_scoreline":"1-1",
    "draw_alternative_expected_points":1.6900041277,
    "draw_alternative_is_competitive":false,
    "home_elo":1828.0933308282,
    "away_elo":1911.6698743289,
    "elo_diff":-83.5765435007
  },
  {
    "date":"2026-06-25",
    "tournament":"FIFA World Cup",
    "home_team":"United States",
    "away_team":"Turkey",
    "model_home_expected_goals":1.6522461221,
    "model_away_expected_goals":1.064288522,
    "home_expected_goals":2.3131445709,
    "away_expected_goals":1.4900039307,
    "goal_inflation":1.4,
    "max_total_candidate_goals":4,
    "draw_probability_multiplier":1.0,
    "home_win_probability":0.5566164896,
    "draw_probability":0.1991328923,
    "away_win_probability":0.2442506181,
    "recommended_home_score":2,
    "recommended_away_score":1,
    "recommended_scoreline":"2-1",
    "recommended_expected_points":3.5965101412,
    "draw_alternative_home_score":1,
    "draw_alternative_away_score":1,
    "draw_alternative_scoreline":"1-1",
    "draw_alternative_expected_points":1.5055079447,
    "draw_alternative_is_competitive":false,
    "home_elo":1870.2654488243,
    "away_elo":1875.0970381561,
    "elo_diff":-4.8315893318
  },
  {
    "date":"2026-06-25",
    "tournament":"FIFA World Cup",
    "home_team":"Tunisia",
    "away_team":"Netherlands",
    "model_home_expected_goals":0.7639747194,
    "model_away_expected_goals":2.2488767469,
    "home_expected_goals":1.0695646071,
    "away_expected_goals":3.1484274457,
    "goal_inflation":1.4,
    "max_total_candidate_goals":4,
    "draw_probability_multiplier":1.0,
    "home_win_probability":0.097397577,
    "draw_probability":0.1309290596,
    "away_win_probability":0.7716733635,
    "recommended_home_score":1,
    "recommended_away_score":3,
    "recommended_scoreline":"1-3",
    "recommended_expected_points":4.649999587,
    "draw_alternative_home_score":1,
    "draw_alternative_away_score":1,
    "draw_alternative_scoreline":"1-1",
    "draw_alternative_expected_points":0.9925871319,
    "draw_alternative_is_competitive":false,
    "home_elo":1723.2682748016,
    "away_elo":1996.0597382435,
    "elo_diff":-272.7914634418
  },
  {
    "date":"2026-06-25",
    "tournament":"FIFA World Cup",
    "home_team":"Japan",
    "away_team":"Sweden",
    "model_home_expected_goals":1.9973806976,
    "model_away_expected_goals":0.8078388885,
    "home_expected_goals":2.7963329767,
    "away_expected_goals":1.1309744438,
    "goal_inflation":1.4,
    "max_total_candidate_goals":4,
    "draw_probability_multiplier":1.0,
    "home_win_probability":0.7135285631,
    "draw_probability":0.1562561068,
    "away_win_probability":0.1302153301,
    "recommended_home_score":2,
    "recommended_away_score":1,
    "recommended_scoreline":"2-1",
    "recommended_expected_points":4.3682779278,
    "draw_alternative_home_score":1,
    "draw_alternative_away_score":1,
    "draw_alternative_scoreline":"1-1",
    "draw_alternative_expected_points":1.1929460031,
    "draw_alternative_is_competitive":false,
    "home_elo":1984.6863732384,
    "away_elo":1785.2169769885,
    "elo_diff":199.4693962499
  },
  {
    "date":"2026-06-25",
    "tournament":"FIFA World Cup",
    "home_team":"Ecuador",
    "away_team":"Germany",
    "model_home_expected_goals":1.2960415743,
    "model_away_expected_goals":1.3010558348,
    "home_expected_goals":1.814458204,
    "away_expected_goals":1.8214781687,
    "goal_inflation":1.4,
    "max_total_candidate_goals":4,
    "draw_probability_multiplier":1.0,
    "home_win_probability":0.3889430265,
    "draw_probability":0.2193261952,
    "away_win_probability":0.3917307783,
    "recommended_home_score":1,
    "recommended_away_score":2,
    "recommended_scoreline":"1-2",
    "recommended_expected_points":2.6771358639,
    "draw_alternative_home_score":1,
    "draw_alternative_away_score":1,
    "draw_alternative_scoreline":"1-1",
    "draw_alternative_expected_points":1.6663243143,
    "draw_alternative_is_competitive":false,
    "home_elo":1947.6143635162,
    "away_elo":1998.3284782599,
    "elo_diff":-50.7141147437
  },
  {
    "date":"2026-06-26",
    "tournament":"FIFA World Cup",
    "home_team":"Norway",
    "away_team":"France",
    "model_home_expected_goals":1.1523570429,
    "model_away_expected_goals":1.9068010866,
    "home_expected_goals":1.6132998601,
    "away_expected_goals":2.6695215212,
    "goal_inflation":1.4,
    "max_total_candidate_goals":4,
    "draw_probability_multiplier":1.0,
    "home_win_probability":0.2236078215,
    "draw_probability":0.1815103317,
    "away_win_probability":0.5948818468,
    "recommended_home_score":1,
    "recommended_away_score":2,
    "recommended_scoreline":"1-2",
    "recommended_expected_points":3.7450771254,
    "draw_alternative_home_score":2,
    "draw_alternative_away_score":2,
    "draw_alternative_scoreline":"2-2",
    "draw_alternative_expected_points":1.3505468333,
    "draw_alternative_is_competitive":false,
    "home_elo":1924.9498446916,
    "away_elo":2096.5675872274,
    "elo_diff":-171.6177425358
  },
  {
    "date":"2026-06-26",
    "tournament":"FIFA World Cup",
    "home_team":"Egypt",
    "away_team":"Iran",
    "model_home_expected_goals":0.9588643328,
    "model_away_expected_goals":1.4330646809,
    "home_expected_goals":1.342410066,
    "away_expected_goals":2.0062905532,
    "goal_inflation":1.4,
    "max_total_candidate_goals":4,
    "draw_probability_multiplier":1.0,
    "home_win_probability":0.2560359177,
    "draw_probability":0.2172007631,
    "away_win_probability":0.5267633191,
    "recommended_home_score":1,
    "recommended_away_score":2,
    "recommended_scoreline":"1-2",
    "recommended_expected_points":3.4848618889,
    "draw_alternative_home_score":1,
    "draw_alternative_away_score":1,
    "draw_alternative_scoreline":"1-1",
    "draw_alternative_expected_points":1.6835999109,
    "draw_alternative_is_competitive":false,
    "home_elo":1782.0685106616,
    "away_elo":1893.4474460293,
    "elo_diff":-111.3789353676
  },
  {
    "date":"2026-06-26",
    "tournament":"FIFA World Cup",
    "home_team":"New Zealand",
    "away_team":"Belgium",
    "model_home_expected_goals":0.8942920056,
    "model_away_expected_goals":2.2410177618,
    "home_expected_goals":1.2520088078,
    "away_expected_goals":3.1374248665,
    "goal_inflation":1.4,
    "max_total_candidate_goals":4,
    "draw_probability_multiplier":1.0,
    "home_win_probability":0.1228291328,
    "draw_probability":0.1417657098,
    "away_win_probability":0.7354051574,
    "recommended_home_score":1,
    "recommended_away_score":3,
    "recommended_scoreline":"1-3",
    "recommended_expected_points":4.4453781493,
    "draw_alternative_home_score":1,
    "draw_alternative_away_score":1,
    "draw_alternative_scoreline":"1-1",
    "draw_alternative_expected_points":1.0539324391,
    "draw_alternative_is_competitive":false,
    "home_elo":1728.972016488,
    "away_elo":1957.2799795586,
    "elo_diff":-228.3079630706
  },
  {
    "date":"2026-06-26",
    "tournament":"FIFA World Cup",
    "home_team":"Uruguay",
    "away_team":"Spain",
    "model_home_expected_goals":0.7768138886,
    "model_away_expected_goals":1.8117428641,
    "home_expected_goals":1.087539444,
    "away_expected_goals":2.5364400097,
    "goal_inflation":1.4,
    "max_total_candidate_goals":4,
    "draw_probability_multiplier":1.0,
    "home_win_probability":0.144904159,
    "draw_probability":0.1722082976,
    "away_win_probability":0.6828875434,
    "recommended_home_score":1,
    "recommended_away_score":2,
    "recommended_scoreline":"1-2",
    "recommended_expected_points":4.2597904226,
    "draw_alternative_home_score":1,
    "draw_alternative_away_score":1,
    "draw_alternative_scoreline":"1-1",
    "draw_alternative_expected_points":1.3321868844,
    "draw_alternative_is_competitive":false,
    "home_elo":1943.8793757479,
    "away_elo":2144.9255019351,
    "elo_diff":-201.0461261872
  },
  {
    "date":"2026-06-26",
    "tournament":"FIFA World Cup",
    "home_team":"Cape Verde",
    "away_team":"Saudi Arabia",
    "model_home_expected_goals":1.0990817666,
    "model_away_expected_goals":1.3290706279,
    "home_expected_goals":1.5387144732,
    "away_expected_goals":1.8606988791,
    "goal_inflation":1.4,
    "max_total_candidate_goals":4,
    "draw_probability_multiplier":1.0,
    "home_win_probability":0.3218005367,
    "draw_probability":0.2245094334,
    "away_win_probability":0.4536900299,
    "recommended_home_score":1,
    "recommended_away_score":2,
    "recommended_scoreline":"1-2",
    "recommended_expected_points":3.0653699175,
    "draw_alternative_home_score":1,
    "draw_alternative_away_score":1,
    "draw_alternative_scoreline":"1-1",
    "draw_alternative_expected_points":1.7310747921,
    "draw_alternative_is_competitive":false,
    "home_elo":1641.479438499,
    "away_elo":1698.0976722276,
    "elo_diff":-56.6182337285
  },
  {
    "date":"2026-06-26",
    "tournament":"FIFA World Cup",
    "home_team":"Senegal",
    "away_team":"Iraq",
    "model_home_expected_goals":1.7784601599,
    "model_away_expected_goals":0.8189213595,
    "home_expected_goals":2.4898442239,
    "away_expected_goals":1.1464899033,
    "goal_inflation":1.4,
    "max_total_candidate_goals":4,
    "draw_probability_multiplier":1.0,
    "home_win_probability":0.6622915323,
    "draw_probability":0.1781882751,
    "away_win_probability":0.1595201926,
    "recommended_home_score":2,
    "recommended_away_score":1,
    "recommended_scoreline":"2-1",
    "recommended_expected_points":4.1588038139,
    "draw_alternative_home_score":1,
    "draw_alternative_away_score":1,
    "draw_alternative_scoreline":"1-1",
    "draw_alternative_expected_points":1.3742895808,
    "draw_alternative_is_competitive":false,
    "home_elo":1871.5491482862,
    "away_elo":1703.2404079939,
    "elo_diff":168.3087402923
  },
  {
    "date":"2026-06-27",
    "tournament":"FIFA World Cup",
    "home_team":"DR Congo",
    "away_team":"Uzbekistan",
    "model_home_expected_goals":1.0199002265,
    "model_away_expected_goals":1.2349359454,
    "home_expected_goals":1.4278603171,
    "away_expected_goals":1.7289103235,
    "goal_inflation":1.4,
    "max_total_candidate_goals":4,
    "draw_probability_multiplier":1.0,
    "home_win_probability":0.3190436996,
    "draw_probability":0.2339479701,
    "away_win_probability":0.4470083303,
    "recommended_home_score":1,
    "recommended_away_score":2,
    "recommended_scoreline":"1-2",
    "recommended_expected_points":3.0504636136,
    "draw_alternative_home_score":1,
    "draw_alternative_away_score":1,
    "draw_alternative_scoreline":"1-1",
    "draw_alternative_expected_points":1.8251398595,
    "draw_alternative_is_competitive":false,
    "home_elo":1728.3589327918,
    "away_elo":1802.2580019002,
    "elo_diff":-73.8990691084
  },
  {
    "date":"2026-06-27",
    "tournament":"FIFA World Cup",
    "home_team":"Jordan",
    "away_team":"Argentina",
    "model_home_expected_goals":0.5883019058,
    "model_away_expected_goals":3.0027305806,
    "home_expected_goals":0.8236226681,
    "away_expected_goals":4.2038228129,
    "goal_inflation":1.4,
    "max_total_candidate_goals":4,
    "draw_probability_multiplier":1.0,
    "home_win_probability":0.0343954904,
    "draw_probability":0.0672917236,
    "away_win_probability":0.898312786,
    "recommended_home_score":0,
    "recommended_away_score":3,
    "recommended_scoreline":"0-3",
    "recommended_expected_points":5.3031381374,
    "draw_alternative_home_score":1,
    "draw_alternative_away_score":1,
    "draw_alternative_scoreline":"1-1",
    "draw_alternative_expected_points":0.5084678379,
    "draw_alternative_is_competitive":false,
    "home_elo":1744.4625195924,
    "away_elo":2157.4074030027,
    "elo_diff":-412.9448834103
  },
  {
    "date":"2026-06-27",
    "tournament":"FIFA World Cup",
    "home_team":"Colombia",
    "away_team":"Portugal",
    "model_home_expected_goals":1.4466038454,
    "model_away_expected_goals":1.297276601,
    "home_expected_goals":2.0252453836,
    "away_expected_goals":1.8161872414,
    "goal_inflation":1.4,
    "max_total_candidate_goals":4,
    "draw_probability_multiplier":1.0,
    "home_win_probability":0.4341562783,
    "draw_probability":0.2121956515,
    "away_win_probability":0.3536480701,
    "recommended_home_score":2,
    "recommended_away_score":1,
    "recommended_scoreline":"2-1",
    "recommended_expected_points":2.907832904,
    "draw_alternative_home_score":1,
    "draw_alternative_away_score":1,
    "draw_alternative_scoreline":"1-1",
    "draw_alternative_expected_points":1.5913503887,
    "draw_alternative_is_competitive":false,
    "home_elo":2042.4549771892,
    "away_elo":2019.7122644869,
    "elo_diff":22.7427127023
  },
  {
    "date":"2026-06-27",
    "tournament":"FIFA World Cup",
    "home_team":"Algeria",
    "away_team":"Austria",
    "model_home_expected_goals":1.2427050776,
    "model_away_expected_goals":1.2850575567,
    "home_expected_goals":1.7397871086,
    "away_expected_goals":1.7990805793,
    "goal_inflation":1.4,
    "max_total_candidate_goals":4,
    "draw_probability_multiplier":1.0,
    "home_win_probability":0.3768682912,
    "draw_probability":0.222385636,
    "away_win_probability":0.4007460728,
    "recommended_home_score":1,
    "recommended_away_score":2,
    "recommended_scoreline":"1-2",
    "recommended_expected_points":2.7400033961,
    "draw_alternative_home_score":1,
    "draw_alternative_away_score":1,
    "draw_alternative_scoreline":"1-1",
    "draw_alternative_expected_points":1.6996871199,
    "draw_alternative_is_competitive":false,
    "home_elo":1866.7300590439,
    "away_elo":1884.1524680474,
    "elo_diff":-17.4224090034
  },
  {
    "date":"2026-06-27",
    "tournament":"FIFA World Cup",
    "home_team":"Panama",
    "away_team":"England",
    "model_home_expected_goals":0.7456631652,
    "model_away_expected_goals":2.3779818816,
    "home_expected_goals":1.0439284312,
    "away_expected_goals":3.3291746342,
    "goal_inflation":1.4,
    "max_total_candidate_goals":4,
    "draw_probability_multiplier":1.0,
    "home_win_probability":0.0843013436,
    "draw_probability":0.1192378544,
    "away_win_probability":0.796460802,
    "recommended_home_score":1,
    "recommended_away_score":3,
    "recommended_scoreline":"1-3",
    "recommended_expected_points":4.7722185757,
    "draw_alternative_home_score":1,
    "draw_alternative_away_score":1,
    "draw_alternative_scoreline":"1-1",
    "draw_alternative_expected_points":0.9005723863,
    "draw_alternative_is_competitive":false,
    "home_elo":1793.5538470601,
    "away_elo":2067.3089633583,
    "elo_diff":-273.7551162981
  },
  {
    "date":"2026-06-27",
    "tournament":"FIFA World Cup",
    "home_team":"Croatia",
    "away_team":"Ghana",
    "model_home_expected_goals":2.1818629394,
    "model_away_expected_goals":0.7565693616,
    "home_expected_goals":3.0546081151,
    "away_expected_goals":1.0591971062,
    "goal_inflation":1.4,
    "max_total_candidate_goals":4,
    "draw_probability_multiplier":1.0,
    "home_win_probability":0.762418716,
    "draw_probability":0.1358852681,
    "away_win_probability":0.101696016,
    "recommended_home_score":3,
    "recommended_away_score":1,
    "recommended_scoreline":"3-1",
    "recommended_expected_points":4.6051844351,
    "draw_alternative_home_score":1,
    "draw_alternative_away_score":1,
    "draw_alternative_scoreline":"1-1",
    "draw_alternative_expected_points":1.0348525532,
    "draw_alternative_is_competitive":false,
    "home_elo":1931.7111995508,
    "away_elo":1653.2031236897,
    "elo_diff":278.5080758611
  }
]