[
  {
    "team":"Argentina",
    "group":"Group 09",
    "round_of_32_probability":1.0,
    "round_of_16_probability":0.879062,
    "quarterfinal_probability":0.524636,
    "semifinal_probability":0.37248,
    "final_probability":0.24794,
    "champion_probability":0.178918,
    "runner_up_probability":0.069022,
    "third_place_probability":0.094146,
    "podium_expected_points":2.812086
  },
  {
    "team":"France",
    "group":"Group 10",
    "round_of_32_probability":1.0,
    "round_of_16_probability":0.861058,
    "quarterfinal_probability":0.473094,
    "semifinal_probability":0.321074,
    "final_probability":0.203758,
    "champion_probability":0.142686,
    "runner_up_probability":0.061072,
    "third_place_probability":0.0866,
    "podium_expected_points":2.348436
  },
  {
    "team":"Spain",
    "group":"Group 08",
    "round_of_32_probability":1.0,
    "round_of_16_probability":0.822,
    "quarterfinal_probability":0.5537,
    "semifinal_probability":0.325494,
    "final_probability":0.180282,
    "champion_probability":0.105744,
    "runner_up_probability":0.074538,
    "third_place_probability":0.094922,
    "podium_expected_points":2.128354
  },
  {
    "team":"Brazil",
    "group":"Group 04",
    "round_of_32_probability":1.0,
    "round_of_16_probability":0.853166,
    "quarterfinal_probability":0.517684,
    "semifinal_probability":0.311334,
    "final_probability":0.144274,
    "champion_probability":0.089336,
    "runner_up_probability":0.054938,
    "third_place_probability":0.110616,
    "podium_expected_points":1.885944
  },
  {
    "team":"Germany",
    "group":"Group 05",
    "round_of_32_probability":1.0,
    "round_of_16_probability":0.822824,
    "quarterfinal_probability":0.541614,
    "semifinal_probability":0.325278,
    "final_probability":0.19467,
    "champion_probability":0.083654,
    "runner_up_probability":0.111016,
    "third_place_probability":0.063348,
    "podium_expected_points":2.041408
  },
  {
    "team":"Portugal",
    "group":"Group 11",
    "round_of_32_probability":1.0,
    "round_of_16_probability":0.744448,
    "quarterfinal_probability":0.450292,
    "semifinal_probability":0.247032,
    "final_probability":0.132498,
    "champion_probability":0.062994,
    "runner_up_probability":0.069504,
    "third_place_probability":0.062188,
    "podium_expected_points":1.496912
  },
  {
    "team":"Netherlands",
    "group":"Group 06",
    "round_of_32_probability":1.0,
    "round_of_16_probability":0.831598,
    "quarterfinal_probability":0.456668,
    "semifinal_probability":0.222048,
    "final_probability":0.10137,
    "champion_probability":0.058776,
    "runner_up_probability":0.042594,
    "third_place_probability":0.074938,
    "podium_expected_points":1.303202
  },
  {
    "team":"England",
    "group":"Group 12",
    "round_of_32_probability":1.0,
    "round_of_16_probability":0.74293,
    "quarterfinal_probability":0.413746,
    "semifinal_probability":0.209044,
    "final_probability":0.100496,
    "champion_probability":0.04349,
    "runner_up_probability":0.057006,
    "third_place_probability":0.054686,
    "podium_expected_points":1.164378
  },
  {
    "team":"Japan",
    "group":"Group 06",
    "round_of_32_probability":1.0,
    "round_of_16_probability":0.652178,
    "quarterfinal_probability":0.390642,
    "semifinal_probability":0.223104,
    "final_probability":0.11063,
    "champion_probability":0.040266,
    "runner_up_probability":0.070364,
    "third_place_probability":0.046372,
    "podium_expected_points":1.197432
  },
  {
    "team":"Mexico",
    "group":"Group 01",
    "round_of_32_probability":1.0,
    "round_of_16_probability":0.783208,
    "quarterfinal_probability":0.404522,
    "semifinal_probability":0.137714,
    "final_probability":0.063118,
    "champion_probability":0.033568,
    "runner_up_probability":0.02955,
    "third_place_probability":0.043326,
    "podium_expected_points":0.78871
  },
  {
    "team":"Colombia",
    "group":"Group 11",
    "round_of_32_probability":1.0,
    "round_of_16_probability":0.708452,
    "quarterfinal_probability":0.387748,
    "semifinal_probability":0.178492,
    "final_probability":0.08208,
    "champion_probability":0.031496,
    "runner_up_probability":0.050584,
    "third_place_probability":0.04249,
    "podium_expected_points":0.932082
  },
  {
    "team":"Morocco",
    "group":"Group 04",
    "round_of_32_probability":1.0,
    "round_of_16_probability":0.575324,
    "quarterfinal_probability":0.323808,
    "semifinal_probability":0.170164,
    "final_probability":0.077406,
    "champion_probability":0.024744,
    "runner_up_probability":0.052662,
    "third_place_probability":0.033854,
    "podium_expected_points":0.838006
  },
  {
    "team":"Canada",
    "group":"Group 02",
    "round_of_32_probability":1.0,
    "round_of_16_probability":0.550216,
    "quarterfinal_probability":0.296866,
    "semifinal_probability":0.147256,
    "final_probability":0.070848,
    "champion_probability":0.02305,
    "runner_up_probability":0.047798,
    "third_place_probability":0.028414,
    "podium_expected_points":0.754954
  },
  {
    "team":"Switzerland",
    "group":"Group 02",
    "round_of_32_probability":1.0,
    "round_of_16_probability":0.727608,
    "quarterfinal_probability":0.340764,
    "semifinal_probability":0.144152,
    "final_probability":0.054898,
    "champion_probability":0.022342,
    "runner_up_probability":0.032556,
    "third_place_probability":0.042678,
    "podium_expected_points":0.697258
  },
  {
    "team":"United States",
    "group":"Group 03",
    "round_of_32_probability":1.0,
    "round_of_16_probability":0.64684,
    "quarterfinal_probability":0.3037,
    "semifinal_probability":0.133884,
    "final_probability":0.063592,
    "champion_probability":0.018976,
    "runner_up_probability":0.044616,
    "third_place_probability":0.024512,
    "podium_expected_points":0.669248
  },
  {
    "team":"Belgium",
    "group":"Group 07",
    "round_of_32_probability":0.873608,
    "round_of_16_probability":0.4159,
    "quarterfinal_probability":0.188902,
    "semifinal_probability":0.082078,
    "final_probability":0.034454,
    "champion_probability":0.00939,
    "runner_up_probability":0.025064,
    "third_place_probability":0.015204,
    "podium_expected_points":0.370432
  },
  {
    "team":"Norway",
    "group":"Group 10",
    "round_of_32_probability":1.0,
    "round_of_16_probability":0.464958,
    "quarterfinal_probability":0.198948,
    "semifinal_probability":0.082786,
    "final_probability":0.030104,
    "champion_probability":0.007588,
    "runner_up_probability":0.022516,
    "third_place_probability":0.015226,
    "podium_expected_points":0.332138
  },
  {
    "team":"Croatia",
    "group":"Group 12",
    "round_of_32_probability":0.90737,
    "round_of_16_probability":0.391266,
    "quarterfinal_probability":0.16057,
    "semifinal_probability":0.060264,
    "final_probability":0.020856,
    "champion_probability":0.00496,
    "runner_up_probability":0.015896,
    "third_place_probability":0.011216,
    "podium_expected_points":0.232848
  },
  {
    "team":"Ivory Coast",
    "group":"Group 05",
    "round_of_32_probability":1.0,
    "round_of_16_probability":0.419848,
    "quarterfinal_probability":0.16913,
    "semifinal_probability":0.064462,
    "final_probability":0.02097,
    "champion_probability":0.004288,
    "runner_up_probability":0.016682,
    "third_place_probability":0.01101,
    "podium_expected_points":0.231386
  },
  {
    "team":"Egypt",
    "group":"Group 07",
    "round_of_32_probability":0.999952,
    "round_of_16_probability":0.403502,
    "quarterfinal_probability":0.138788,
    "semifinal_probability":0.040352,
    "final_probability":0.011764,
    "champion_probability":0.002408,
    "runner_up_probability":0.009356,
    "third_place_probability":0.007558,
    "podium_expected_points":0.136718
  },
  {
    "team":"Iran",
    "group":"Group 07",
    "round_of_32_probability":0.708224,
    "round_of_16_probability":0.249468,
    "quarterfinal_probability":0.090744,
    "semifinal_probability":0.031668,
    "final_probability":0.010616,
    "champion_probability":0.002186,
    "runner_up_probability":0.00843,
    "third_place_probability":0.00517,
    "podium_expected_points":0.11515
  },
  {
    "team":"Australia",
    "group":"Group 03",
    "round_of_32_probability":1.0,
    "round_of_16_probability":0.326362,
    "quarterfinal_probability":0.114958,
    "semifinal_probability":0.035714,
    "final_probability":0.012022,
    "champion_probability":0.002138,
    "runner_up_probability":0.009884,
    "third_place_probability":0.004982,
    "podium_expected_points":0.125362
  },
  {
    "team":"Senegal",
    "group":"Group 10",
    "round_of_32_probability":0.946368,
    "round_of_16_probability":0.22725,
    "quarterfinal_probability":0.066746,
    "semifinal_probability":0.017702,
    "final_probability":0.00536,
    "champion_probability":0.001916,
    "runner_up_probability":0.003444,
    "third_place_probability":0.005126,
    "podium_expected_points":0.072342
  },
  {
    "team":"Austria",
    "group":"Group 09",
    "round_of_32_probability":0.739258,
    "round_of_16_probability":0.251758,
    "quarterfinal_probability":0.08842,
    "semifinal_probability":0.030082,
    "final_probability":0.009238,
    "champion_probability":0.001748,
    "runner_up_probability":0.00749,
    "third_place_probability":0.004748,
    "podium_expected_points":0.10114
  },
  {
    "team":"Ecuador",
    "group":"Group 05",
    "round_of_32_probability":1.0,
    "round_of_16_probability":0.243124,
    "quarterfinal_probability":0.081088,
    "semifinal_probability":0.022096,
    "final_probability":0.004248,
    "champion_probability":0.001284,
    "runner_up_probability":0.002964,
    "third_place_probability":0.006364,
    "podium_expected_points":0.068372
  },
  {
    "team":"Sweden",
    "group":"Group 06",
    "round_of_32_probability":1.0,
    "round_of_16_probability":0.245262,
    "quarterfinal_probability":0.065862,
    "semifinal_probability":0.013054,
    "final_probability":0.001886,
    "champion_probability":0.000508,
    "runner_up_probability":0.001378,
    "third_place_probability":0.003262,
    "podium_expected_points":0.032414
  },
  {
    "team":"Algeria",
    "group":"Group 09",
    "round_of_32_probability":0.624894,
    "round_of_16_probability":0.164294,
    "quarterfinal_probability":0.046306,
    "semifinal_probability":0.01181,
    "final_probability":0.002704,
    "champion_probability":0.000416,
    "runner_up_probability":0.002288,
    "third_place_probability":0.00171,
    "podium_expected_points":0.031014
  },
  {
    "team":"Uruguay",
    "group":"Group 08",
    "round_of_32_probability":0.304466,
    "round_of_16_probability":0.07479,
    "quarterfinal_probability":0.022988,
    "semifinal_probability":0.007042,
    "final_probability":0.002278,
    "champion_probability":0.000404,
    "runner_up_probability":0.001874,
    "third_place_probability":0.001096,
    "podium_expected_points":0.024512
  },
  {
    "team":"South Africa",
    "group":"Group 01",
    "round_of_32_probability":1.0,
    "round_of_16_probability":0.182524,
    "quarterfinal_probability":0.04187,
    "semifinal_probability":0.008348,
    "final_probability":0.001728,
    "champion_probability":0.000168,
    "runner_up_probability":0.00156,
    "third_place_probability":0.000824,
    "podium_expected_points":0.01828
  },
  {
    "team":"Cape Verde",
    "group":"Group 08",
    "round_of_32_probability":0.55838,
    "round_of_16_probability":0.13129,
    "quarterfinal_probability":0.030744,
    "semifinal_probability":0.00714,
    "final_probability":0.001484,
    "champion_probability":0.000166,
    "runner_up_probability":0.001318,
    "third_place_probability":0.000672,
    "podium_expected_points":0.015564
  },
  {
    "team":"Ghana",
    "group":"Group 12",
    "round_of_32_probability":0.999252,
    "round_of_16_probability":0.167924,
    "quarterfinal_probability":0.03436,
    "semifinal_probability":0.005968,
    "final_probability":0.001002,
    "champion_probability":0.000114,
    "runner_up_probability":0.000888,
    "third_place_probability":0.00077,
    "podium_expected_points":0.012094
  },
  {
    "team":"Paraguay",
    "group":"Group 03",
    "round_of_32_probability":0.998176,
    "round_of_16_probability":0.145992,
    "quarterfinal_probability":0.029728,
    "semifinal_probability":0.00329,
    "final_probability":0.000468,
    "champion_probability":0.000104,
    "runner_up_probability":0.000364,
    "third_place_probability":0.000732,
    "podium_expected_points":0.007612
  },
  {
    "team":"South Korea",
    "group":"Group 01",
    "round_of_32_probability":0.39746,
    "round_of_16_probability":0.039438,
    "quarterfinal_probability":0.005892,
    "semifinal_probability":0.00127,
    "final_probability":0.000242,
    "champion_probability":0.000074,
    "runner_up_probability":0.000168,
    "third_place_probability":0.000274,
    "podium_expected_points":0.003454
  },
  {
    "team":"Bosnia and Herzegovina",
    "group":"Group 02",
    "round_of_32_probability":1.0,
    "round_of_16_probability":0.118788,
    "quarterfinal_probability":0.018818,
    "semifinal_probability":0.002576,
    "final_probability":0.000252,
    "champion_probability":0.000042,
    "runner_up_probability":0.00021,
    "third_place_probability":0.000456,
    "podium_expected_points":0.00438
  },
  {
    "team":"DR Congo",
    "group":"Group 11",
    "round_of_32_probability":0.365396,
    "round_of_16_probability":0.061464,
    "quarterfinal_probability":0.013244,
    "semifinal_probability":0.001894,
    "final_probability":0.000204,
    "champion_probability":0.00004,
    "runner_up_probability":0.000164,
    "third_place_probability":0.000332,
    "podium_expected_points":0.003372
  },
  {
    "team":"Saudi Arabia",
    "group":"Group 08",
    "round_of_32_probability":0.423064,
    "round_of_16_probability":0.054962,
    "quarterfinal_probability":0.009238,
    "semifinal_probability":0.001362,
    "final_probability":0.000196,
    "champion_probability":0.000014,
    "runner_up_probability":0.000182,
    "third_place_probability":0.000122,
    "podium_expected_points":0.002206
  },
  {
    "team":"New Zealand",
    "group":"Group 07",
    "round_of_32_probability":0.109622,
    "round_of_16_probability":0.016708,
    "quarterfinal_probability":0.002976,
    "semifinal_probability":0.000466,
    "final_probability":0.00006,
    "champion_probability":0.000004,
    "runner_up_probability":0.000056,
    "third_place_probability":0.000052,
    "podium_expected_points":0.000748
  },
  {
    "team":"Scotland",
    "group":"Group 04",
    "round_of_32_probability":0.023052,
    "round_of_16_probability":0.00116,
    "quarterfinal_probability":0.000094,
    "semifinal_probability":0.000016,
    "final_probability":0.000002,
    "champion_probability":0.0,
    "runner_up_probability":0.000002,
    "third_place_probability":0.000002,
    "podium_expected_points":0.000026
  },
  {
    "team":"Panama",
    "group":"Group 12",
    "round_of_32_probability":0.008176,
    "round_of_16_probability":0.00045,
    "quarterfinal_probability":0.000044,
    "semifinal_probability":0.000004,
    "final_probability":0.000002,
    "champion_probability":0.0,
    "runner_up_probability":0.000002,
    "third_place_probability":0.000002,
    "podium_expected_points":0.000026
  },
  {
    "team":"Uzbekistan",
    "group":"Group 11",
    "round_of_32_probability":0.004202,
    "round_of_16_probability":0.00016,
    "quarterfinal_probability":0.000012,
    "semifinal_probability":0.000004,
    "final_probability":0.0,
    "champion_probability":0.0,
    "runner_up_probability":0.0,
    "third_place_probability":0.0,
    "podium_expected_points":0.0
  },
  {
    "team":"Jordan",
    "group":"Group 09",
    "round_of_32_probability":0.00908,
    "round_of_16_probability":0.000446,
    "quarterfinal_probability":0.000046,
    "semifinal_probability":0.000002,
    "final_probability":0.0,
    "champion_probability":0.0,
    "runner_up_probability":0.0,
    "third_place_probability":0.0,
    "podium_expected_points":0.0
  },
  {
    "team":"Curaçao",
    "group":"Group 05",
    "round_of_32_probability":0.0,
    "round_of_16_probability":0.0,
    "quarterfinal_probability":0.0,
    "semifinal_probability":0.0,
    "final_probability":0.0,
    "champion_probability":0.0,
    "runner_up_probability":0.0,
    "third_place_probability":0.0,
    "podium_expected_points":0.0
  },
  {
    "team":"Czech Republic",
    "group":"Group 01",
    "round_of_32_probability":0.0,
    "round_of_16_probability":0.0,
    "quarterfinal_probability":0.0,
    "semifinal_probability":0.0,
    "final_probability":0.0,
    "champion_probability":0.0,
    "runner_up_probability":0.0,
    "third_place_probability":0.0,
    "podium_expected_points":0.0
  },
  {
    "team":"Haiti",
    "group":"Group 04",
    "round_of_32_probability":0.0,
    "round_of_16_probability":0.0,
    "quarterfinal_probability":0.0,
    "semifinal_probability":0.0,
    "final_probability":0.0,
    "champion_probability":0.0,
    "runner_up_probability":0.0,
    "third_place_probability":0.0,
    "podium_expected_points":0.0
  },
  {
    "team":"Iraq",
    "group":"Group 10",
    "round_of_32_probability":0.0,
    "round_of_16_probability":0.0,
    "quarterfinal_probability":0.0,
    "semifinal_probability":0.0,
    "final_probability":0.0,
    "champion_probability":0.0,
    "runner_up_probability":0.0,
    "third_place_probability":0.0,
    "podium_expected_points":0.0
  },
  {
    "team":"Qatar",
    "group":"Group 02",
    "round_of_32_probability":0.0,
    "round_of_16_probability":0.0,
    "quarterfinal_probability":0.0,
    "semifinal_probability":0.0,
    "final_probability":0.0,
    "champion_probability":0.0,
    "runner_up_probability":0.0,
    "third_place_probability":0.0,
    "podium_expected_points":0.0
  },
  {
    "team":"Tunisia",
    "group":"Group 06",
    "round_of_32_probability":0.0,
    "round_of_16_probability":0.0,
    "quarterfinal_probability":0.0,
    "semifinal_probability":0.0,
    "final_probability":0.0,
    "champion_probability":0.0,
    "runner_up_probability":0.0,
    "third_place_probability":0.0,
    "podium_expected_points":0.0
  },
  {
    "team":"Turkey",
    "group":"Group 03",
    "round_of_32_probability":0.0,
    "round_of_16_probability":0.0,
    "quarterfinal_probability":0.0,
    "semifinal_probability":0.0,
    "final_probability":0.0,
    "champion_probability":0.0,
    "runner_up_probability":0.0,
    "third_place_probability":0.0,
    "podium_expected_points":0.0
  }
]